Workbook

Sheet Master_Extraction
A1: Paper_ID | B1: File_Name | C1: PDF_Path_or_Link | D1: Extraction_Status | E1: Extraction_Date | F1: Reviewer_Check_Status | G1: Human_Reviewer | H1: Confidence_Overall_1_5 | I1: Notes_For_Human_Check | J1: DOI | K1: Title | L1: Authors | M1: Year | N1: Publication_Type | O1: Venue_Journal_Conference | P1: Publisher | Q1: Discipline_Field | R1: Keywords_Author_Provided | S1: Abstract_Short | T1: Inclusion_Decision | U1: Relevance_to_Review_1_5 | V1: LCNC_Focus_Level | W1: Study_Object | X1: Primary_LCNC_Topic | Y1: Secondary_Topics | Z1: Review_Question_Link | AA1: Why_This_Paper_Matters | AB1: Definition_of_Low_Code | AC1: Definition_of_No_Code | AD1: Related_Terms_Used | AE1: Theoretical_Framework | AF1: Key_Constructs | AG1: Boundary_or_Scope_Conditions | AH1: Paper_Category | AI1: Research_Type | AJ1: Study_Design | AK1: Research_Method | AL1: Data_Type | AM1: Unit_of_Analysis | AN1: Industry_Domain | AO1: Application_Domain | AP1: Target_User_Group | AQ1: Platform_or_Tool_Studied | AR1: Technology_Stack_or_Ecosystem | AS1: Research_Questions_or_Hypotheses | AT1: Data_Source | AU1: Sample_Size | AV1: Sampling_Strategy | AW1: Participants_Profile | AX1: Time_Period | AY1: Location_Context | AZ1: Instruments_Used | BA1: Variables_or_Measures | BB1: Analysis_Techniques | BC1: Validity_Reliability_Checks | BD1: Main_Findings_Detailed | BE1: Claimed_Benefits | BF1: Claimed_Challenges | BG1: Security_Privacy_Findings | BH1: Governance_Findings | BI1: Scalability_Maintainability_Findings | BJ1: Productivity_Findings | BK1: Quality_Findings | BL1: Skills_Role_Findings | BM1: Education_Training_Findings | BN1: AI_Automation_Findings | BO1: Economic_or_Business_Findings | BP1: Contradictions_or_Nuances | BQ1: Authors_Interpretation | BR1: Key_Quote_1 | BS1: Key_Quote_1_Page | BT1: Key_Quote_2 | BU1: Key_Quote_2_Page | BV1: Most_Important_Table_Figure | BW1: Important_Statistics_or_Numbers | BX1: Evidence_Strength | BY1: Evidence_Notes | BZ1: Authors_Limitations | CA1: Your_Critical_Limitations | CB1: Research_Gaps_Identified | CC1: Future_Work_Suggested | CD1: Practical_Implications | CE1: Theoretical_Implications | CF1: Policy_Governance_Implications | CG1: Theme_Code_1 | CH1: Theme_Code_2 | CI1: Theme_Code_3 | CJ1: Theme_Code_4 | CK1: Method_Code | CL1: Domain_Code | CM1: Quality_Score_Total | CN1: Quality_Rating | CO1: Use_In_Final_Review | CP1: Best_Section_For_Citation | CQ1: Suggested_Claim_This_Paper_Supports | CR1: Contrasts_With_Papers | CS1: Cluster_Group | CT1: One_Sentence_Takeaway | CU1: Agent_Uncertainty_Flags | CV1: Citation_BibTeX | CW1: APA_Reference | CX1: Source_URL
A2: P001 | B2: 1.AI-FOR-SCIENCE LOW-CODE PLATFORM WITH.pdf | C2: research paper\1.AI-FOR-SCIENCE LOW-CODE PLATFORM WITH.pdf | D2: Completed | E2: 2026-06-12 | F2: Checked - OK | G2: Reported | H2: 4 | I2: Verify automated title/authors/method/sample/theme coding and exact quote page numbers before publication use. | J2: Not reported | K2: AI-for-Science Low-code Platform with Bayesian Adversarial Multi-Agent Framework | L2: Zihang Zeng1,2#, Jiaquan Zhang1,2#, Pengze Li1, Yuan Qi1,3, Xi Chen1,3† | M2: 2025 | N2: Preprint | O2: Published as a conference paper at ICLR 2026; arXiv:2603.03233v1 [cs.AI] 3 Mar 2026; Published as a conference paper at ICLR 2026 | P2: Not reported | Q2: Unclear: discipline not explicitly labeled; paper text concerns LCNC/software systems | R2: Not reported | S2: Multi-agent systems leveraging Large Language Models (LLMs) show immense potential for solving complex scientific problems. However, their reliability is undermined by the probabilistic nature of LLMs, which can produce hallucinations in both generated code and its corresponding test cases. In a multi-agent architecture, these errors can propagate and compound, leading to flawed final outputs. To overcome these core limitations, we introduce a novel Bayesian Adversarial Multi-agent Framework for AI for Science (AI4S). Delivered as a Low-code Platform (LCP), our framework enhances the coding capability for scientific tasks across a wide range of base models, from 1.7B open-source LLMs to up-to-date commercial ones. Our framework employs three agents in a recursive loop that adversarially co-optimizes the generated solutions, the test cases used for evaluation, and the prompts driving generation. This process is governed by a non-LLM-based Bayesian updating rule, which systematically reduces evaluation uncertainty and mitigates the system’s dependence on any single LLM’s reliability. Furthermore, the LCP empowers domain experts by translating high-level natural language prompts into executable, domain-specific requirements, eliminating the need for intricate prompt engineering. Extensive experiments confirm that our framework generates robust solutions while effectively minimizing error propagation. On a complex, cross-disciplinary Earth Science benchmark, our platform demonstrates superior reliability and outperforms state-of-the-art models, where a 32B opensource model c... | T2: Include | U2: 5 | V2: Core focus | W2: AI-for-Science Low-code Platform with Bayesian Adversarial Multi-Agent Framework | X2: AI and automation | Y2: Quality assurance and testing; Platform comparison; Education and training | Z2: Supports review questions on LCNC adoption, AI automation, methods, benefits, risks, and gaps depending on assigned theme codes. | AA2: Extensive experiments confirm that our framework generates robust solutions while effectively minimizing error propagation. | On a complex, cross-disciplinary Earth Science benchmark, our platform demonstrates superior reliability and outperforms state-of-the-art models, where a 32B opensource model can beat the performance of a 235B model in the ScienceCode benchmark with our framework. | Standard unit tests may miss critical scientific constraints, theoretical foundations, or domain-specifi... | AB2: Published as a conference paper at ICLR 2026 AI-FOR-SCIENCELOW-CODEPLATFORM WITH BAYESIANADVERSARIALMULTI-AGENTFRAMEWORK Zihang Zeng1,2#, Jiaquan Zhang1,2#, Pengze Li1, Yuan Qi1,3, Xi Chen1,3† 1Artificial Intelligence Innovation and Incubation Institute, Fudan University 2Shanghai Innovation Institute 3Shanghai Academy of AI for Science x_chen@fudan.edu.cn ABSTRACT Multi-agent systems leveraging Large Language Models (LLMs) show immense potential for solving complex scientific problems. | AC2: Not reported | AD2: low-code | AE2: Published as a conference paper at ICLR 2026 AI-FOR-SCIENCELOW-CODEPLATFORM WITH BAYESIANADVERSARIALMULTI-AGENTFRAMEWORK Zihang Zeng1,2#, Jiaquan Zhang1,2#, Pengze Li1, Yuan Qi1,3, Xi Chen1,3† 1Artificial Intelligence Innovation and Incubation Institute, Fudan University 2Shanghai Innovation Institute 3Shanghai Academy of AI for Science x_chen@fudan.edu.cn ABSTRACT Multi-agent systems leveraging Large Language Models (LLMs) show immense potential for solving complex scientific problems. | AF2: low-code | AG2: Multi-agent systems leveraging Large Language Models (LLMs) show immense potential for solving complex scientific problems. However, their reliability is undermined by the probabilistic nature of LLMs, which can produce hallucinations in both generated code and its corresponding test cases. In a multi-agent architecture, these errors can propagate and compound, leading to flawed final outputs. To overcome these core limitations, we introduce a novel Bayesian Adversarial Multi-agent Framework for AI for Science (AI4S). Delivered as a Low-code Platform (LCP), our framework enhances the coding capability for scientific tasks across a wide range of base models, from 1.7B open-source LLMs to up-to-date commercial ones. Our framework employs three agents in a recursive loop that adversarially co-optimizes the generated solutions, the test cases used for evaluation, and the prompts driving generation. This process is governed by a non-LLM-based Bayesian updating rule, which systematically reduces evaluation uncertainty and mitigates the system’s dependence on any single LLM’s reliability. Furthermore, the LCP empowers domain experts by translating high-level natural language prompts into executable, domain-specific requirements, eliminating the need for intricate prompt engineering. Extensive experiments confirm that our framework generates robust solutions while effectively minimizing error propagation. On a complex, cross-disciplinary Earth Science benchmark, our platform demonstrates superior reliability and outperforms state-of-the-art models, where a 32B opensource model c... | AH2: Tool/Platform Proposal | AI2: Technical/Engineering | AJ2: Benchmarking | AK2: Benchmarking | AL2: Primary Data | AM2: Prototype/tool/platform or benchmark tasks | AN2: scientific; AI for Science | AO2: scientific; AI for Science | AP2: Furthermore, the LCP empowers domain experts by translating high-level natural language prompts into executable, domain-specific requirements, eliminating the need for intricate prompt engineering. | AQ2: Not reported | AR2: low-code | AS2: Not reported | AT2: On a complex, cross-disciplinary Earth Science benchmark, our platform demonstrates superior reliability and outperforms state-of-the-art models, where a 32B opensource model can beat the performance of a 235B model in the ScienceCode benchmark with our framework. | AU2: Not reported | AV2: Subsequently, the TM agent generates an initial set of test cases ( Test Case0) corresponding to these sub-tasks and other criteria derived from prior knowledge. | AW2: Furthermore, the LCP empowers domain experts by translating high-level natural language prompts into executable, domain-specific requirements, eliminating the need for intricate prompt engineering. | AX2: Not reported | AY2: Not reported | AZ2: On a complex, cross-disciplinary Earth Science benchmark, our platform demonstrates superior reliability and outperforms state-of-the-art models, where a 32B opensource model can beat the performance of a 235B model in the ScienceCode benchmark with our framework. | BA2: On a complex, cross-disciplinary Earth Science benchmark, our platform demonstrates superior reliability and outperforms state-of-the-art models, where a 32B opensource model can beat the performance of a 235B model in the ScienceCode benchmark with our framework. | The gains are particularly striking for open-source models, with relative improvements of up to87.1%(for Qwen3-8b). | As shown in Table 2, our LCP framework achieves new state-ofthe-art (SOTA) performance, particularly in the Valid Execution Rate (VER), where it scores90.2% (without knowledge) and87.3%(with knowledge), far surpassing all other methods. | Table 1: Model Performance Comparison on SciCode with various backbone models Without Knowledge With Knowledge Without Knowledge With Knowledge Model Method Sub (%) Main (%) Sub (%) Main (%) Model Method Sub (%) Main (%) Sub (%) Main (%) Qwen3-8b Baseline 13.2 0 19.8 1.5 GPT-4o Baseline 24.1 1.5 33.7 7.7Ours24.7(87.1%) 4.6 27.4(38.4%) 4.6Ours37.... | BB2: Delivered as a Low-code Platform (LCP), our framework enhances the coding capability for scientific tasks across a wide range of base models, from 1.7B open-source LLMs to up-to-date commercial ones. | BC2: However, their reliability is undermined by the probabilistic nature of LLMs, which can produce hallucinations in both generated code and its corresponding test cases. | BD2: Extensive experiments confirm that our framework generates robust solutions while effectively minimizing error propagation. | On a complex, cross-disciplinary Earth Science benchmark, our platform demonstrates superior reliability and outperforms state-of-the-art models, where a 32B opensource model can beat the performance of a 235B model in the ScienceCode benchmark with our framework. | Standard unit tests may miss critical scientific constraints, theoretical foundations, or domain-specific limitations. | BE2: This process is governed by a non-LLM-based Bayesian updating rule, which systematically reduces evaluation uncertainty and mitigates the system’s dependence on any single LLM’s reliability. | Furthermore, the LCP empowers domain experts by translating high-level natural language prompts into executable, domain-specific requirements, eliminating the need for intricate prompt engineering. | BF2: Published as a conference paper at ICLR 2026 AI-FOR-SCIENCELOW-CODEPLATFORM WITH BAYESIANADVERSARIALMULTI-AGENTFRAMEWORK Zihang Zeng1,2#, Jiaquan Zhang1,2#, Pengze Li1, Yuan Qi1,3, Xi Chen1,3† 1Artificial Intelligence Innovation and Incubation Institute, Fudan University 2Shanghai Innovation Institute 3Shanghai Academy of AI for Science x_chen@fudan.edu.cn ABSTRACT Multi-agent systems leveraging Large Language Models (LLMs) show immense potent... | However, their reliability is undermined by the probabilistic nature of LLMs, which can produce hallucinations in both generated code and its corresponding test cases. | BG2: Not reported | BH2: This plan is iteratively refined based on users’ feedback F and refinements until user’s approval and denoted as Plans, as indicated by Loop 1 of Figure 2. | BI2: On a complex, cross-disciplinary Earth Science benchmark, our platform demonstrates superior reliability and outperforms state-of-the-art models, where a 32B opensource model can beat the performance of a 235B model in the ScienceCode benchmark with our framework. | This fundamental insight motivates our core design philosophy: an adversarial co-evolution framework where test case generation and code improvement mutually refine each other through competitive optimization, replacing traditional static verification approaches. | BJ2: Not reported | BK2: 2.3 A PRIORI ESTIMATION WITHBAYESIANOPTIMIZATION We noticed that executing all the generated codes for testing can be computationally expensive. | BL2: It maintains accessibility for non-technical domain experts while fully leveraging their domain expertise without requiring any computer science or professional prompt engineering skills. | BM2: Furthermore, evaluating the generated machine learning or deep learning models can be highly resource-intensive, and performance variability due to training dynamics and data poses an additional challenge to the update mechanism. | BN2: Published as a conference paper at ICLR 2026 AI-FOR-SCIENCELOW-CODEPLATFORM WITH BAYESIANADVERSARIALMULTI-AGENTFRAMEWORK Zihang Zeng1,2#, Jiaquan Zhang1,2#, Pengze Li1, Yuan Qi1,3, Xi Chen1,3† 1Artificial Intelligence Innovation and Incubation Institute, Fudan University 2Shanghai Innovation Institute 3Shanghai Academy of AI for Science x_chen@fudan.edu.cn ABSTRACT Multi-agent systems leveraging Large Language Models (LLMs) show immense potential for solving complex scientific problems. | BO2: This suggests an optimal balance between performance and computational cost. | BP2: However, their reliability is undermined by the probabilistic nature of LLMs, which can produce hallucinations in both generated code and its corresponding test cases. | BQ2: Extensive experiments confirm that our framework generates robust solutions while effectively minimizing error propagation. | On a complex, cross-disciplinary Earth Science benchmark, our platform demonstrates superior reliability and outperforms state-of-the-art models, where a 32B opensource model can beat the performance of a 235B model in the ScienceCode benchmark with our framework. | Standard unit tests may miss critical scientific constraints, theoretical foundations, or domain-specific limitations. | BR2: Published as a conference paper at ICLR 2026 AI-FOR-SCIENCELOW-CODEPLATFORM WITH BAYESIANADVERSARIALMULTI-AGENTFRAMEWORK Zihang Zeng1,2#, Jiaquan Zhang1,2#, Pengze Li1, Yuan Qi1,3, Xi Chen1,3† 1Artificial Intelligence Innovation and Incubation Institute, Fudan University 2Shanghai Innovation Institute 3Shanghai Academy of AI for Science x_chen@fudan.edu.cn ABSTRACT Multi-agent systems leveraging Large Language Models (LLMs) show immense potential for solving complex scientific problems. | BS2: 1 | BT2: 2.3 A PRIORI ESTIMATION WITHBAYESIANOPTIMIZATION We noticed that executing all the generated codes for testing can be computationally expensive. | BU2: 5 | BV2: Not reported | BW2: On a complex, cross-disciplinary Earth Science benchmark, our platform demonstrates superior reliability and outperforms state-of-the-art models, where a 32B opensource model can beat the performance of a 235B model in the ScienceCode benchmark with our framework. | The gains are particularly striking for open-source models, with relative improvements of up to87.1%(for Qwen3-8b). | As shown in Table 2, our LCP framework achieves new state-ofthe-art (SOTA) performance, particularly in the Valid Execution Rate (VER), where it scores90.2% (without knowledge) and87.3%(with knowledge), far surpassing all other methods. | Table 1: Model Performance Comparison on SciCode with various backbone models Without Knowledge With Knowledge Without Knowledge With Knowledge Model Method Sub (%) Main (%) Sub (%) Main (%) Model Method Sub (%) Main (%) Sub (%) Main (%) Qwen3-8b Baseline 13.2 0 19.8 1.5 GPT-4o Baseline 24.1 1.5 33.7 7.7Ours24.7(87.1%) 4.6 27.4(38.4%) 4.6Ours37.... | BX2: Strong | BY2: PDF text extracted from 38 pages; sample evidence page: Not reported. | BZ2: , we introduce a novel Bayesian Adversarial Multi-agent Framework for AI for Science (AI4S). Delivered as a Low-code Platform (LCP), our framework enhances the coding capability for scientific tasks across a wide range of base models, from 1.7B open-source LLMs to up-to-date commercial ones. Our framework employs three agents in a recursive loop that adversarially co-optimizes the generated solutions, the test cases used for evaluation, and the prompts driving generation. This process is governed by a non-LLM-based Bayesian updating rule, which systematically reduces evaluation uncertainty and mitigates the system’s dependence on any single LLM’s reliability. Furthermore, the LCP empowers domain experts by translating high-level natural language prompts into executable, domain-specific requirements, eliminating the need for intricate prompt engineering. Extensive experiments confirm that our framework generates robust solutions while effectively minimizing error propagation. On a complex, cross-disciplinary Earth Science benchmark, our platform demonstrates superior reliability and outperforms state-of-the-art models, where a 32B opensource model can beat the performance of a 235B model in the ScienceCode benchmark with our framework. 1 INTRODUCTION Large Language Models (LLMs) are transforming AI for Science (AI4S) research paradigm by automating complex scientific code gen... | CA2: Sample/data adequacy could not be verified from parsed text | CB2: will focus on extending the Bayesian updates to handle multi-modal inputs, such as equations and diagrams, and optimizing the iteration protocols for large-scale scientific simulations. | CC2: will focus on extending the Bayesian updates to handle multi-modal inputs, such as equations and diagrams, and optimizing the iteration protocols for large-scale scientific simulations. | CD2: While this increased token budget can be a practical constraint for long pipelines, in reliability-critical scientific applications, we prioritize executable correctness and robustness over marginal token savings. | CE2: Not reported | CF2: This plan is iteratively refined based on users’ feedback F and refinements until user’s approval and denoted as Plans, as indicated by Loop 1 of Figure 2. | CG2: AI_AUTOMATION | CH2: QUALITY_TESTING | CI2: PLATFORM_COMPARISON | CJ2: EDUCATION | CK2: Benchmarking | CL2: Not reported | CM2: =IFERROR(VLOOKUP($A2,Quality_Appraisal!$A:$P,15,FALSE),"") -> 23 | CN2: =IFERROR(VLOOKUP($A2,Quality_Appraisal!$A:$P,16,FALSE),"") -> Strong | CO2: Yes - central | CP2: Findings/Future | CQ2: Extensive experiments confirm that our framework generates robust solutions while effectively minimizing error propagation. | On a complex, cross-disciplinary Earth Science benchmark, our platform demonstrates superior reliability and outperforms state-of-the-art models, where a 32B opensource model can beat the performance of a 235B model in the ScienceCode benchmark with our framework. | Standard unit tests may miss critical scientific constraints, theoretical foundations, or domain-specifi... | CR2: Not reported | CS2: AI and automation | CT2: Extensive experiments confirm that our framework generates robust solutions while effectively minimizing error propagation. | On a complex, cross-disciplinary Earth Science benchmark, our platform demonstrates superior reliability and outperforms state-of-the-art models, where a 32B opensource model can beat the performance of a 235B model in the ScienceCode benchmark with our framework. | Standard unit tests may miss critical scientific constraints, theoretical foundations, or domain-specifi... | CU2: sample/data size missing | CV2: Not reported | CW2: Zihang Zeng1,2#, Jiaquan Zhang1,2#, Pengze Li1, Yuan Qi1,3, Xi Chen1,3† (2025). AI-for-Science Low-code Platform with Bayesian Adversarial Multi-Agent Framework. Published as a conference paper at ICLR 2026; arXiv:2603.03233v1 [cs.AI] 3 Mar 2026; Published as a conference paper at ICLR 2026. | CX2: Not reported
A3: P002 | B3: 2.LOW-CODE AND NO-CODE WITH BESSER TO CREATE AND.pdf | C3: research paper\2.LOW-CODE AND NO-CODE WITH BESSER TO CREATE AND.pdf | D3: Completed | E3: 2026-06-12 | F3: Checked - OK | G3: Reported | H3: 4 | I3: Verify automated title/authors/method/sample/theme coding and exact quote page numbers before publication use. | J3: Not reported | K3: Low-code and no-code with BESSER to create and deploy smart web applications | L3: arXiv:2605.07376v1 [cs.SE] 8 May 2026 | M3: 2025 | N3: Preprint | O3: The peer-reviewed paper will be published in the proceedings of ICWE 2026.; arXiv:2605.07376v1 [cs.SE] 8 May 2026 | P3: Not reported | Q3: Unclear: discipline not explicitly labeled; paper text concerns LCNC/software systems | R3: Low-code·No-code·Web application·Agents 1 | S3: The increasing demand for web applications containing AI-agents, seen as smart web applications, has prompted the need for new techniques to facilitate their creation. Low-code has risen as an approach that reduces the amount of handwritten code by focusing on the abstraction of components in the form of models combined with automated generators to produce applications. Existing low-code platforms are commercial, leading to drawbacks such as the risk of vendor lock-in, limited extensibility, and more. We present the open-source BESSER low-code framework, which allows users to design, generate and deploy their application via a freely accessible web-based editor, while guaranteeing transparency and extensibility. KeywordsLow-code·No-code·Web application·Agents | T3: Include | U3: 5 | V3: Core focus | W3: Low-code and no-code with BESSER to create and deploy smart web applications | X3: Model-driven / visual programming roots | Y3: AI and automation; Maintainability; Platform comparison | Z3: Supports review questions on LCNC adoption, AI automation, methods, benefits, risks, and gaps depending on assigned theme codes. | AA3: Languages such as IFML [2], OOWS [3], or UWE [4] are often seen as foundational for the development of traditional UIs. | 2 Demonstration Figure 1 presents the part of BESSER’s pipeline for developing smart web applications used in the demonstration. | The demonstration contains the example of a web application of a library, with a conversational agent responding to frequently asked questions. | AB3: Existing low-code platforms are commercial, leading to drawbacks such as the risk of vendor lock-in, limited extensibility, and more. | AC3: From theGUIperspective, the editor provides a no-code interface that allows users to drag and drop UI components onto a blank page (Figure 2), which are immediately rendered. | AD3: low-code; no-code; model-driven engineering | AE3: We present the open-source BESSER low-code framework, which allows users to design, generate and deploy their application via a freely accessible web-based editor, while guaranteeing transparency and extensibility. | AF3: Low-code·No-code·Web application·Agents 1 | AG3: The increasing demand for web applications containing AI-agents, seen as smart web applications, has prompted the need for new techniques to facilitate their creation. Low-code has risen as an approach that reduces the amount of handwritten code by focusing on the abstraction of components in the form of models combined with automated generators to produce applications. Existing low-code platforms are commercial, leading to drawbacks such as the risk of vendor lock-in, limited extensibility, and more. We present the open-source BESSER low-code framework, which allows users to design, generate and deploy their application via a freely accessible web-based editor, while guaranteeing transparency and extensibility. KeywordsLow-code·No-code·Web application·Agents | AH3: Empirical Study | AI3: Qualitative | AJ3: Document Analysis | AK3: Document Analysis | AL3: Secondary Data | AM3: Not reported | AN3: Not reported | AO3: Not reported | AP3: We present the open-source BESSER low-code framework, which allows users to design, generate and deploy their application via a freely accessible web-based editor, while guaranteeing transparency and extensibility. | AQ3: BESSER | AR3: BESSER | AS3: Not reported | AT3: The only additional requirement to complete the demo is a free account on GitHub 2 and Render3, the former being used for hosting the models and generated code, and the latter for running frontend and backend servers. | AU3: Not reported | AV3: Thestructuralperspective specifies the static aspects of the web application through class diagrams, including classes, attributes, methods, relationships, and other elements, reusing core UML [ 6] concepts for this perspective while extending and simplifying selected aspects of the specification for smart web applications. | AW3: We present the open-source BESSER low-code framework, which allows users to design, generate and deploy their application via a freely accessible web-based editor, while guaranteeing transparency and extensibility. | AX3: Not reported | AY3: Not reported | AZ3: Yet, these do not cover the definition of smart components, and provide limited or fragmented tool support for the complete creation and deployment pipeline. | BA3: A video demonstration of the presented scenario is available4 3 Modeling, generating and deploying smart web applications with BESSER BESSER provides the B-UML (BESSER-UML) language, which enables the modeling of smart web applications via three complementary but still interrelated perspectives:structural,agent, andGUIperspectives. | BB3: Not reported | BC3: Not reported | BD3: Languages such as IFML [2], OOWS [3], or UWE [4] are often seen as foundational for the development of traditional UIs. | 2 Demonstration Figure 1 presents the part of BESSER’s pipeline for developing smart web applications used in the demonstration. | The demonstration contains the example of a web application of a library, with a conversational agent responding to frequently asked questions. | BE3: Low-code has risen as an approach that reduces the amount of handwritten code by focusing on the abstraction of components in the form of models combined with automated generators to produce applications. | KeywordsLow-code·No-code·Web application·Agents 1 Introduction The increasing demand for better software in recent years has created a need for advanced strategies to improve developer productivity. | BF3: Existing low-code platforms are commercial, leading to drawbacks such as the risk of vendor lock-in, limited extensibility, and more. | Low-code development, the latest reincarnation of model-driven engineering approaches, addresses this demand but introduces challenges related to the growing complexity of modern software requirements, such as AI-powered agents. | BG3: Not reported | BH3: These actions may include textual responses (e.g., for chat interactions), calls to Python methods (e.g., to invoke external APIs), or operations driven by Large Language Model (LLM) outputs, combining the controlled output from state machines with the openness of LLMs. | BI3: Existing low-code platforms are commercial, leading to drawbacks such as the risk of vendor lock-in, limited extensibility, and more. | BJ3: KeywordsLow-code·No-code·Web application·Agents 1 Introduction The increasing demand for better software in recent years has created a need for advanced strategies to improve developer productivity. | BK3: Not reported | BL3: Not reported | BM3: Not reported | BN3: The reference will be provided once available. arXiv:2605.07376v1 [cs.SE] 8 May 2026 | BO3: Not reported | BP3: Low-code development, the latest reincarnation of model-driven engineering approaches, addresses this demand but introduces challenges related to the growing complexity of modern software requirements, such as AI-powered agents. | BQ3: Languages such as IFML [2], OOWS [3], or UWE [4] are often seen as foundational for the development of traditional UIs. | 2 Demonstration Figure 1 presents the part of BESSER’s pipeline for developing smart web applications used in the demonstration. | The demonstration contains the example of a web application of a library, with a conversational agent responding to frequently asked questions. | BR3: Low-code development, the latest reincarnation of model-driven engineering approaches, addresses this demand but introduces challenges related to the growing complexity of modern software requirements, such as AI-powered agents. | BS3: 2 | BT3: LOW-CODE AND NO-CODE WITHBESSERTO CREATE AND DEPLOY SMART WEB APPLICATIONS Iván Alfonso Luxembourg Institute of Science and Technology, Luxembourg ivan.alfonso@list.lu Armen Sulejmani Luxembourg Institute of Science and Technology, Luxembourg armen.sulejmani@list.lu Aaron Conrardy Luxembourg Institute of Science and Technology, Luxembourg University of Luxembourg, Luxembourg aaron.conrardy@list.lu Jordi Cabot Luxembourg Institute of Science and Technology, Luxembourg University of Luxembourg, Luxembourg jordi.cabot@list.lu ABSTRACT The increasing demand for web applications containing AI-agents, seen as smart web applications, has prompted the need for new techniques to facilitate their creation. | BU3: 2 | BV3: Not reported | BW3: A video demonstration of the presented scenario is available4 3 Modeling, generating and deploying smart web applications with BESSER BESSER provides the B-UML (BESSER-UML) language, which enables the modeling of smart web applications via three complementary but still interrelated perspectives:structural,agent, andGUIperspectives. | BX3: Moderate | BY3: PDF text extracted from 5 pages; sample evidence page: Not reported. | BZ3: Not reported | CA3: Sample/data adequacy could not be verified from parsed text; No explicit author limitations section found in parsed text | CB3: Not reported | CC3: Not reported | CD3: Not reported | CE3: Not reported | CF3: These actions may include textual responses (e.g., for chat interactions), calls to Python methods (e.g., to invoke external APIs), or operations driven by Large Language Model (LLM) outputs, combining the controlled output from state machines with the openness of LLMs. | CG3: MDE_VISUAL_PROGRAMMING | CH3: AI_AUTOMATION | CI3: MAINTAINABILITY | CJ3: PLATFORM_COMPARISON | CK3: Document Analysis | CL3: Not reported | CM3: =IFERROR(VLOOKUP($A3,Quality_Appraisal!$A:$P,15,FALSE),"") -> 17 | CN3: =IFERROR(VLOOKUP($A3,Quality_Appraisal!$A:$P,16,FALSE),"") -> Moderate | CO3: Yes - central | CP3: Background | CQ3: Languages such as IFML [2], OOWS [3], or UWE [4] are often seen as foundational for the development of traditional UIs. | 2 Demonstration Figure 1 presents the part of BESSER’s pipeline for developing smart web applications used in the demonstration. | The demonstration contains the example of a web application of a library, with a conversational agent responding to frequently asked questions. | CR3: Not reported | CS3: Model-driven / visual programming roots | CT3: Languages such as IFML [2], OOWS [3], or UWE [4] are often seen as foundational for the development of traditional UIs. | 2 Demonstration Figure 1 presents the part of BESSER’s pipeline for developing smart web applications used in the demonstration. | The demonstration contains the example of a web application of a library, with a conversational agent responding to frequently asked questions. | CU3: sample/data size missing; limitations not found | CV3: Not reported | CW3: arXiv:2605.07376v1 [cs.SE] 8 May 2026 (2025). Low-code and no-code with BESSER to create and deploy smart web applications. The peer-reviewed paper will be published in the proceedings of ICWE 2026.; arXiv:2605.07376v1 [cs.SE] 8 May 2026. | CX3: Not reported
A4: P003 | B4: 3.Design Behaviour and Interface Consistency in Generative No-Code Tools A Systematic Literature Review.pdf | C4: research paper\3.Design Behaviour and Interface Consistency in Generative No-Code Tools A Systematic Literature Review.pdf | D4: Completed | E4: 2026-06-12 | F4: Checked - OK | G4: Reported | H4: 4 | I4: Verify automated title/authors/method/sample/theme coding and exact quote page numbers before publication use. | J4: 10.3390/computers15040238 | K4: Design Behaviour and Interface Consistency in Generative No-Code Tools: A Systematic Literature Review | L4: No-Code Tools: A Systematic Literature Review; Gizem Irmak 1,2, * and Qusay H. Mahmoud 1 | M4: 2021 | N4: Review Paper | O4: Licensee MDPI, Basel, Switzerland. | P4: MDPI | Q4: Unclear: discipline not explicitly labeled; paper text concerns LCNC/software systems | R4: generative AI; no-code tools; user interface design; reproducibility; usability; accessibility; ethics 1. | S4: Generative no-code development tools enable users to create applications directly from natural-language prompts, shifting interface design from manual construction to AImediated generation. However, identical prompts frequently produce substantially different user interface (UI) outcomes across tools and even across repeated executions within the same tool. This paper presents a systematic literature review examining how generative no-code systems make design and aesthetic decisions with respect to layout structure, visual consistency, usability, accessibility, and reproducibility. Twenty peer-reviewed studies (2021-2025) were analyzed following a structured review protocol. Existing research predominantly evaluates usability and accessibility in isolation while providing limited insight into aesthetic coherence, design variability, and prompt-to-output stability. Across studies, generative tools exhibit implicit design priors and stochastic behavior that lead to inconsistent visual outcomes and partial misalignment with human-centered design principles. These findings indicate that generative no-code tools do not act as deterministic translators of user intent but instead introduce their own stylistic tendencies. The paper identifies critical evaluation gaps and outlines requirements for future systems, including reproducible generation, transparent design reasoning, and user-directed control, to support reliable and predictable interface development. | T4: Include | U4: 5 | V4: Core focus | W4: Design Behaviour and Interface Consistency in Generative No-Code Tools: A Systematic Literature Review | X4: AI and automation | Y4: Platform comparison; Usability and user experience; Enterprise adoption | Z4: Supports review questions on LCNC adoption, AI automation, methods, benefits, risks, and gaps depending on assigned theme codes. | AA4: These findings indicate that generative no-code tools do not act as deterministic translators of user intent but instead introduce their own stylistic tendencies. | Study Year Methodology and Focus Key Findings and Limitations Zhou T. [15] 2025 Design-to-code pipeline using computer vision and multimodal LLMs to generate UI code from mockups and screenshots. | Study Year Methodology and Focus Key Findings and Limitations Wan Y. [17] 2025 Divide-and-conquer UI generation pipeline using multimo... | AB4: Introduction Low-code/no-code (LCNC) platforms have transformed software development by offering visual environments and pre-built components that require minimal or no programming knowledge. | AC4: Mahmoud 1 1 Department of Electrical, Computer, and Software Engineering, Ontario Tech University, Oshawa, ON L1G 0C5, Canada; qusay.mahmoud@ontariotechu.ca 2 Department of Control and Computer Engineering, Politecnico di Torino, 10129 Torino, Italy * Correspondence: gizem.irmak@studenti.polito.it Abstract Generative no-code development tools enable users to create applications directly from natural-language prompts, shifting interface design from manual construction to AImediated generation. | AD4: low-code; no-code; LCNC; citizen development; visual programming | AE4: Study Year Methodology and Focus Key Findings and Limitations Xu H. [29] 2025 Knowledge-augmented framework using visual prompting and retrieval-augmented generation to convert UI wireframes into React applications. | AF4: generative AI; no-code tools; user interface design; reproducibility; usability; accessibility; ethics 1. | AG4: Generative no-code development tools enable users to create applications directly from natural-language prompts, shifting interface design from manual construction to AImediated generation. However, identical prompts frequently produce substantially different user interface (UI) outcomes across tools and even across repeated executions within the same tool. This paper presents a systematic literature review examining how generative no-code systems make design and aesthetic decisions with respect to layout structure, visual consistency, usability, accessibility, and reproducibility. Twenty peer-reviewed studies (2021-2025) were analyzed following a structured review protocol. Existing research predominantly evaluates usability and accessibility in isolation while providing limited insight into aesthetic coherence, design variability, and prompt-to-output stability. Across studies, generative tools exhibit implicit design priors and stochastic behavior that lead to inconsistent visual outcomes and partial misalignment with human-centered design principles. These findings indicate that generative no-code tools do not act as deterministic translators of user intent but instead introduce their own stylistic tendencies. The paper identifies critical evaluation gaps and outlines requirements for future systems, including reproducible generation, transparent design reasoning, and user-directed control, to support reliable and predictable interface development. | AH4: Literature Review | AI4: Review | AJ4: Systematic Review | AK4: Systematic Review | AL4: Secondary Data | AM4: Published studies/articles | AN4: education | AO4: education | AP4: Mahmoud 1 1 Department of Electrical, Computer, and Software Engineering, Ontario Tech University, Oshawa, ON L1G 0C5, Canada; qusay.mahmoud@ontariotechu.ca 2 Department of Control and Computer Engineering, Politecnico di Torino, 10129 Torino, Italy * Correspondence: gizem.irmak@studenti.polito.it Abstract Generative no-code development tools enable users to create applications directly from natural-language prompts, shifting interface design... | AQ4: AutoGen Studio; ChatGPT | AR4: AutoGen Studio; ChatGPT | AS4: Research Questions This study was guided by one main research question (MRQ) and four supporting sub-questions designed to examine how generative AI-based no-code tools make UI design decisions, how consistent these decisions are, and how well they align with established design principles. • MRQ: How do generative AI-based no-code tools make user interface (UI) design and aesthetic decisions when generating applications from natural-language p... | The protocol defined the research questions, search strategy, eligibility criteria, quality assessment, and data extraction procedures before the search was conducted. | UI Quality Dimension Number of Studies ( n = 20) Layout & Structure 10 Aesthetics & Visual Design 5 Usability & Learnability 5 Accessibility 4 Consistency & Variability 7 Individual studies may contribute to multiple research questions, reflecting the multifaceted nature of generative UI design and evaluation. | AT4: Duan P . [19] 2024 Introduces UICrit dataset with expert UI critiques and applies visually guided few-shot prompting for design feedback generation. | AU4: Frequency of UI quality dimensions assessed across included studies (n = 20). | AV4: In user interface (UI) development, Multimodal Large Language Models (MLLMs) can translate sketches, screenshots, or natural-language descriptions directly into functional code (UI2Code) [5]. | AW4: Mahmoud 1 1 Department of Electrical, Computer, and Software Engineering, Ontario Tech University, Oshawa, ON L1G 0C5, Canada; qusay.mahmoud@ontariotechu.ca 2 Department of Control and Computer Engineering, Politecnico di Torino, 10129 Torino, Italy * Correspondence: gizem.irmak@studenti.polito.it Abstract Generative no-code development tools enable users to create applications directly from natural-language prompts, shifting interface design... | AX4: Database Search Strings Used Total Retrieved Records After Initial Screening IEEE Xplore No-code/low-code AND generative AI/LLM AND UI design 54 44 ACM Digital Library No-code/low-code AND user experience/UI design 60 27 Google Scholar No-code UI design AND evaluation/prompt-based tools 30 18 Searches were restricted to peer-reviewed publication... | AY4: Not reported | AZ4: Systematic Review Design Behaviour and Interface Consistency in Generative No-Code Tools: A Systematic Literature Review Gizem Irmak 1,2, * and Qusay H. | BA4: Adoption is expected to continue growing, with projections indicating use in nearly 70% of enterprise applications by 2025 [3] and approximately 65% of software projects overall [4]. | Computers 2026, 15, 238 2 of 25 models to generate new content and automate development tasks, enhancing LCNC environments by supporting ideation, prototyping, and feature refinement [1]. | Pinho D. [42] 2023 Systematic literature review of 38 studies on usability in low-code platforms. | P . [4] 2024 Systematic literature review of 15 studies on low-code development features, benefits, and challenges. | BB4: Existing research predominantly evaluates usability and accessibility in isolation while providing limited insight into aesthetic coherence, design variability, and prompt-to-output stability. | BC4: Section 7 outlines threats to validity, and Section 8 concludes the paper. | BD4: These findings indicate that generative no-code tools do not act as deterministic translators of user intent but instead introduce their own stylistic tendencies. | Study Year Methodology and Focus Key Findings and Limitations Zhou T. [15] 2025 Design-to-code pipeline using computer vision and multimodal LLMs to generate UI code from mockups and screenshots. | Study Year Methodology and Focus Key Findings and Limitations Wan Y. [17] 2025 Divide-and-conquer UI generation pipeline using multimodal LLMs to decompose screenshots and generate HTML/CSS. | BE4: LCNC solutions are widely adopted because they accelerate development, reduce labor costs, and improve agility, thereby addressing traditional challenges such as delayed delivery and high implementation effort [2]. | While these systems improve development efficiency and accessibility, they also introduce constraints related to scalability, customization, and control, which become particularly relevant in the context of AI-driven interface generation [12]. | BF4: However, identical prompts frequently produce substantially different user interface (UI) outcomes across tools and even across repeated executions within the same tool. | LCNC solutions are widely adopted because they accelerate development, reduce labor costs, and improve agility, thereby addressing traditional challenges such as delayed delivery and high implementation effort [2]. | BG4: Not reported | BH4: Identifies governance risks and mitigation strategies; does not address user-facing UI design or generative interface behavior. | BI4: While these systems improve development efficiency and accessibility, they also introduce constraints related to scalability, customization, and control, which become particularly relevant in the context of AI-driven interface generation [12]. | A. [10], Feng S. [49] Interaction logic Static layout generation Incomplete navigation and cross-page coherence Zhou T. [15] Code usability Structured output in advanced systems Manual effort required for maintainability Zhou T. [15], Wan Y. [17] 5.4. | BJ4: Both approaches abstract implementation details through graphical development environments, enabling faster application creation while reducing reliance on traditional programming. | BK4: Because large language models operate probabilistically, identical prompts may produce different outputs, complicating testing and reproducibility [ 9]. | BL4: Highlights human-AI collaboration in UI design; limited to prototype-level evaluation without analysis of reproducibility or cross-tool variability. | BM4: Highlights workflow trade-offs and educational implications; limited evaluation of detailed UI design and generative variability. | BN4: The integration of LCNC platforms with Generative Artificial Intelligence (GenAI) represents a further shift in software creation workflows. | BO4: This accessibility has contributed to the “democratization” of software creation, enabling non-technical professionals, often referred to as citizen developers, to construct applications quickly and cost-effectively [1]. | BP4: However, identical prompts frequently produce substantially different user interface (UI) outcomes across tools and even across repeated executions within the same tool. | BQ4: These findings indicate that generative no-code tools do not act as deterministic translators of user intent but instead introduce their own stylistic tendencies. | Study Year Methodology and Focus Key Findings and Limitations Zhou T. [15] 2025 Design-to-code pipeline using computer vision and multimodal LLMs to generate UI code from mockups and screenshots. | Study Year Methodology and Focus Key Findings and Limitations Wan Y. [17] 2025 Divide-and-conquer UI generation pipeline using multimodal LLMs to decompose screenshots and generate HTML/CSS. | BR4: The integration of LCNC platforms with Generative Artificial Intelligence (GenAI) represents a further shift in software creation workflows. | BS4: 1 | BT4: Guthardt T. [40] 2024 Empirical comparison of programmers and citizen developers using a prototype no-code builder. | BU4: 7 | BV4: Not reported | BW4: Adoption is expected to continue growing, with projections indicating use in nearly 70% of enterprise applications by 2025 [3] and approximately 65% of software projects overall [4]. | Computers 2026, 15, 238 2 of 25 models to generate new content and automate development tasks, enhancing LCNC environments by supporting ideation, prototyping, and feature refinement [1]. | Pinho D. [42] 2023 Systematic literature review of 38 studies on usability in low-code platforms. | P . [4] 2024 Systematic literature review of 15 studies on low-code development features, benefits, and challenges. | BX4: Strong | BY4: PDF text extracted from 25 pages; sample evidence page: p. 12. | BZ4: inherent to LCNC platforms, such as scalability constraints, hidden platform bugs, and accumulated technical debt, can propagate into generated applications and further reduce reliability [3,22]. 3. Related Work Generative no-code UI research spans three primary directions: platform-oriented studies on low-code/no-code ecosystems, empirical evaluations of AI-generated interfaces, and accessibility or usability assessments. While these works (see Table 2) provide valuable insights into productivity and compliance, they rarely examine design consistency, aesthetic reasoning, or reproducibility across generated interfaces. Consequently, existing literature offers fragmented perspectives on UI quality rather than an integrated understanding of automated design behavior. Table 2. Key related studies on generative no-code and AI-assisted UI design. Study Year Methodology and Focus Key Findings and Limitations Zhou T. [15] 2025 Design-to-code pipeline using computer vision and multimodal LLMs to generate UI code from mockups and screenshots. Structural accuracy; lacks user-centered evaluation. https://doi.org/10.3390/computers15040238 Computers 2026, 15, 238 5 of 25 Table 2. Cont. Study Year Methodology and Focus Key Findings and Limitations Wan Y. [17] 2025 Divide-and-conquer UI generation pipeline using multimodal LLMs to decompose screenshots and generate HTML/CSS. Focus on fide... | CA4: Automated extraction should be checked against the PDF for high-impact fields | CB4: should investigate: • how users form mental models of generative behavior • how interfaces communicate degrees of confidence or stability • how users constrain exploration without over-specifying solutions • how iterative refinement affects trust and perceived control In this context, prompting functions as an ongoing negotiation process. Interfaces that expose alternatives, preserve state across iterations, and communicate change boundaries may improve user confidence and reduce corrective interaction cycles. 6.6. Implications for Software Engineering Research Generative interface development alters the nature of software artifacts from fixed implementations to variable outputs produced by a generation process. As a result, engineering practices must evaluate reliability of the process rather than correctness of a single instance. Quality assurance therefore shifts toward: https://doi.org/10.3390/computers15040238 Computers 2026, 15, 238 21 of 25 • managing prompt and model configu... | CC4: should investigate: • how users form mental models of generative behavior • how interfaces communicate degrees of confidence or stability • how users constrain exploration without over-specifying solutions • how iterative refinement affects trust and perceived control In this context, prompting functions as an ongoing negotiation process. Interfaces that expose alternatives, preserve state across iterations, and communicate change boundaries may improve user confidence and reduce corrective interaction cycles. 6.6. Implications for Software Engineering Research Generative interface development alters the nature of software artifacts from fixed implementations to variable outputs produced by a generation process. As a result, engineering practices must evaluate reliability of the process rather than correctness of a single instance. Quality assurance therefore shifts toward: https://doi.org/10.3390/computers15040238 Computers 2026, 15, 238 21 of 25 • managing prompt and model configu... | CD4: Rather than redefining their general characteristics, this section focuses on their role within contemporary software ecosystems and their implications for automated interface generation. | CE4: Not reported | CF4: Identifies governance risks and mitigation strategies; does not address user-facing UI design or generative interface behavior. | CG4: AI_AUTOMATION | CH4: PLATFORM_COMPARISON | CI4: USABILITY_UX | CJ4: ENTERPRISE_ADOPTION | CK4: Systematic Review | CL4: Not reported | CM4: =IFERROR(VLOOKUP($A4,Quality_Appraisal!$A:$P,15,FALSE),"") -> 24 | CN4: =IFERROR(VLOOKUP($A4,Quality_Appraisal!$A:$P,16,FALSE),"") -> Strong | CO4: Yes - central | CP4: Findings/Future | CQ4: These findings indicate that generative no-code tools do not act as deterministic translators of user intent but instead introduce their own stylistic tendencies. | Study Year Methodology and Focus Key Findings and Limitations Zhou T. [15] 2025 Design-to-code pipeline using computer vision and multimodal LLMs to generate UI code from mockups and screenshots. | Study Year Methodology and Focus Key Findings and Limitations Wan Y. [17] 2025 Divide-and-conquer UI generation pipeline using multimo... | CR4: Not reported | CS4: AI and automation | CT4: These findings indicate that generative no-code tools do not act as deterministic translators of user intent but instead introduce their own stylistic tendencies. | Study Year Methodology and Focus Key Findings and Limitations Zhou T. [15] 2025 Design-to-code pipeline using computer vision and multimodal LLMs to generate UI code from mockups and screenshots. | Study Year Methodology and Focus Key Findings and Limitations Wan Y. [17] 2025 Divide-and-conquer UI generation pipeline using multimo... | CU4: None beyond normal human verification of automated extraction | CV4: Not reported | CW4: No-Code Tools: A Systematic Literature Review; Gizem Irmak 1,2, * and Qusay H. Mahmoud 1 (2021). Design Behaviour and Interface Consistency in Generative No-Code Tools: A Systematic Literature Review. Licensee MDPI, Basel, Switzerland.. | CX4: https://doi.org/10.3390/computers15040238
A5: P004 | B5: 4.LLM4FaaS No-Code Application Development using LLMs.pdf | C5: research paper\4.LLM4FaaS No-Code Application Development using LLMs.pdf | D5: Completed | E5: 2026-06-12 | F5: Checked - OK | G5: Reported | H5: 4 | I5: Verify automated title/authors/method/sample/theme coding and exact quote page numbers before publication use. | J5: 10.1145/3773274.3774686 | K5: LLM4FaaS: No-Code Application Development using LLMs and FaaS | L5: Minghe Wang; Tobias Pfandzelter; Trever Schirmer | M5: 2025 | N5: Preprint | O5: ACM Reference Format:; for redistribution. The definitive Version of Record was published in2025 IEEE/ACM; 18th International Conference on Utility and Cloud Computing (UCC ’25), December 1-4, | P5: IEEE | Q5: Unclear: discipline not explicitly labeled; paper text concerns LCNC/software systems | R5: Large Language Models, Function-as-a-Service, No-Code Development ACM Reference Format: Minghe Wang, Tobias Pfandzelter, Trever Schirmer, and David Bermbach. 2025. LLM4FaaS: No-Code Application Development using LLMs and FaaS. UCC ’25, December 1-4, 2025, Nantes, France ©2025 Copyright held by the owner/author(s). This is the author’s version of th | S5: Large language models (LLMs) show great capabilities in generating code from natural language descriptions, bringing programming power closer to non-technical users. However, their lack of expertise in operating the generated code remains a key barrier to realizing customized applications. Function-as-a-Service (FaaS) platforms offer a high level of abstraction for code execution and deployment, allowing users to run LLM-generated code without requiring technical expertise or incurring operational overhead. In this paper, we present LLM4FaaS, a no-code application development approach that integrates LLMs and FaaS platforms to enable non-technical users to build and run customized applications using only natural language. By deploying LLM-generated code through FaaS, LLM4FaaS abstracts away infrastructure management and boilerplate code generation. We implement a proof-of-concept prototype based on an open-source FaaS platform, and evaluate it using real prompts from non-technical users. Experiments withGPT-4o show that LLM4FaaS can automatically build and deploy code in 71.47% of cases, outperforming a non-FaaS baseline at 43.48% and an existing LLM-based platform at 14.55%, narrowing the gap to human performance at 88.99%. Further analysis of code quality, programming language diversity, latency, and consistency demonstrates a balanced performance in terms of efficiency, maintainability and availability. CCS Concepts •Computing methodologies → Natural language processing;•Computer systems organization → Cloud computing;• Human-centered computing→User centered design. | T5: Include | U5: 5 | V5: Core focus | W5: LLM4FaaS: No-Code Application Development using LLMs and FaaS | X5: AI and automation | Y5: Platform comparison; Quality assurance and testing; Enterprise adoption | Z5: Supports review questions on LCNC adoption, AI automation, methods, benefits, risks, and gaps depending on assigned theme codes. | AA5: Experiments withGPT-4o show that LLM4FaaS can automatically build and deploy code in 71.47% of cases, outperforming a non-FaaS baseline at 43.48% and an existing LLM-based platform at 14.55%, narrowing the gap to human performance at 88.99%. | Further analysis of code quality, programming language diversity, latency, and consistency demonstrates a balanced performance in terms of efficiency, maintainability and availability. | With a 71.47% semantic and 87.55% syntax pass rate, LLM4FaaS demon... | AB5: For example, Liu et al. [20] empirically compare LLM-based and traditional low-code development by analyzing Stack Overflow discussions, showing that LLM assistance enables a broader range of automation scenarios. | AC5: In this paper, we present LLM4FaaS, a no-code application development approach that integrates LLMs and FaaS platforms to enable non-technical users to build and run customized applications using only natural language. | AD5: low-code; no-code; zero-code | AE5: Not reported | AF5: Large Language Models, Function-as-a-Service, No-Code Development ACM Reference Format: Minghe Wang, Tobias Pfandzelter, Trever Schirmer, and David Bermbach. 2025. LLM4FaaS: No-Code Application Development using LLMs and FaaS. UCC ’25, December 1-4, 2025, Nantes, France ©2025 Copyright held by the owner/author(s). This is the author’s version of th | AG5: Large language models (LLMs) show great capabilities in generating code from natural language descriptions, bringing programming power closer to non-technical users. However, their lack of expertise in operating the generated code remains a key barrier to realizing customized applications. Function-as-a-Service (FaaS) platforms offer a high level of abstraction for code execution and deployment, allowing users to run LLM-generated code without requiring technical expertise or incurring operational overhead. In this paper, we present LLM4FaaS, a no-code application development approach that integrates LLMs and FaaS platforms to enable non-technical users to build and run customized applications using only natural language. By deploying LLM-generated code through FaaS, LLM4FaaS abstracts away infrastructure management and boilerplate code generation. We implement a proof-of-concept prototype based on an open-source FaaS platform, and evaluate it using real prompts from non-technical users. Experiments withGPT-4o show that LLM4FaaS can automatically build and deploy code in 71.47% of cases, outperforming a non-FaaS baseline at 43.48% and an existing LLM-based platform at 14.55%, narrowing the gap to human performance at 88.99%. Further analysis of code quality, programming language diversity, latency, and consistency demonstrates a balanced performance in terms of efficiency, maintainability and availability. CCS Concepts •Computing methodologies → Natural language processing;•Computer systems organization → Cloud computing;• Human-centered computing→User centered design. | AH5: Tool/Platform Proposal | AI5: Technical/Engineering | AJ5: Prototype Evaluation | AK5: Prototype Evaluation | AL5: Primary Data | AM5: Prototype/tool/platform or benchmark tasks | AN5: IoT | AO5: IoT | AP5: LLM4FaaS: No-Code Application Development using LLMs and FaaS Minghe Wang TU Berlin Berlin, Germany mw@3s.tu-berlin.de Tobias Pfandzelter TU Berlin Berlin, Germany tp@3s.tu-berlin.de Trever Schirmer TU Berlin Berlin, Germany ts@3s.tu-berlin.de David Bermbach TU Berlin Berlin, Germany db@3s.tu-berlin.de Abstract Large language models (LLMs) show great capabilities in generating code from natural language descriptions, bringing programming power... | AQ5: LLM4FaaS | AR5: LLM4FaaS | AS5: Not reported | AT5: We make all artifacts and dataset used to produce this paper available publicly. | AU5: 4.2.1 Dataset.We collect the dataset through a questionnaire completed by 26 users without prior programming experience. | AV5: As both metrics quantify proportions of cases meeting the respective pass criteria, we omit error bars from the figures. | AW5: LLM4FaaS: No-Code Application Development using LLMs and FaaS Minghe Wang TU Berlin Berlin, Germany mw@3s.tu-berlin.de Tobias Pfandzelter TU Berlin Berlin, Germany tp@3s.tu-berlin.de Trever Schirmer TU Berlin Berlin, Germany ts@3s.tu-berlin.de David Bermbach TU Berlin Berlin, Germany db@3s.tu-berlin.de Abstract Large language models (LLMs) show great capabilities in generating code from natural language descriptions, bringing programming power... | AX5: Not reported | AY5: Not reported | AZ5: LLMs excel in a wide range of natural language tasks, including text generation, translation, and code-related activities, e.g., generation, modification, and verification, making them valuable tools for software engineering [3, 14, 19, 24, 31, 34, 37]. | BA5: Experiments withGPT-4o show that LLM4FaaS can automatically build and deploy code in 71.47% of cases, outperforming a non-FaaS baseline at 43.48% and an existing LLM-based platform at 14.55%, narrowing the gap to human performance at 88.99%. | With a 71.47% semantic and 87.55% syntax pass rate, LLM4FaaS demonstrates promising feasibility and consistent performance in our evaluation. | In the questionnaire, we ask users to describe in natural language how they would instruct a smart home system to automate 4 tasks with increasing complexity. | The average syntactic pass rate for human developers, LLM4FaaS and the baseline are 96.53%, 87.55%, and 88.42%, respectively, while Open Interpreter achieves 31.69%. | BB5: We implement a proof-of-concept prototype based on an open-source FaaS platform, and evaluate it using real prompts from non-technical users. | BC5: Experimental results show that LLM4FaaS achieves high reliability, efficiency and availability while maintaining competitive code quality, making it a viable solution for non-technical users to develop and run tailored applications without requiring any technical expertise. | BD5: Experiments withGPT-4o show that LLM4FaaS can automatically build and deploy code in 71.47% of cases, outperforming a non-FaaS baseline at 43.48% and an existing LLM-based platform at 14.55%, narrowing the gap to human performance at 88.99%. | Further analysis of code quality, programming language diversity, latency, and consistency demonstrates a balanced performance in terms of efficiency, maintainability and availability. | With a 71.47% semantic and 87.55% syntax pass rate, LLM4FaaS demonstrates promising feasibility and consistent performance in our evaluation. | BE5: For this, we present LLM4FaaS, a no-code application development approach for non-technical end-users, leveraging (i) the natural language processing capabilities of LLMs to transform user requirements into code snippets and (ii) FaaS abstractions to streamline code generation, accelerating and simplifying the application development process. | These features support real-time responsiveness to changing workloads, accelerate development, reduce time-to-market, and facilitate rapid iteration on key functionality. | BF5: However, their lack of expertise in operating the generated code remains a key barrier to realizing customized applications. | However, while nontechnical users can use LLMs to generate code for their desired functionality, they typically lack the expertise to properly deploy and run the generated code. | BG5: Not reported | BH5: However, given the latency concern and the rate limit errors observed in the Open Interpreter experiment, the feedback loops may inherently introduce throughput bottlenecks due to rate limit policies of LLM services. | BI5: We believe that the Functionas-a-Service (FaaS) paradigm and its no-ops principle can help: FaaS platforms offer a scalable, event-driven, and fine-grained infrastructure abstraction [2, 9, 11, 18, 21, 22, 26, 28, 33, 35, 36]. | Further analysis of code quality, programming language diversity, latency, and consistency demonstrates a balanced performance in terms of efficiency, maintainability and availability. | BJ5: These features support real-time responsiveness to changing workloads, accelerate development, reduce time-to-market, and facilitate rapid iteration on key functionality. | BK5: Experimental results show that LLM4FaaS achieves high reliability, efficiency and availability while maintaining competitive code quality, making it a viable solution for non-technical users to develop and run tailored applications without requiring any technical expertise. | BL5: Although the advanced natural language interpretation ability of LLMs is a promising avenue for the involvement of individuals without programming skills in software development [3, 6, 29], operational concerns remain a considerable barrier. | BM5: 2.1 LLMs in Software Engineering LLMs are deep learning models trained on extensive text corpora to understand, generate, and manipulate human language. | BN5: However, their lack of expertise in operating the generated code remains a key barrier to realizing customized applications. | BO5: Users can interact with the deployed function through predefined interfaces, while the FaaS platform manages execution, scaling, and resource allocation. | BP5: However, their lack of expertise in operating the generated code remains a key barrier to realizing customized applications. | BQ5: Experiments withGPT-4o show that LLM4FaaS can automatically build and deploy code in 71.47% of cases, outperforming a non-FaaS baseline at 43.48% and an existing LLM-based platform at 14.55%, narrowing the gap to human performance at 88.99%. | Further analysis of code quality, programming language diversity, latency, and consistency demonstrates a balanced performance in terms of efficiency, maintainability and availability. | With a 71.47% semantic and 87.55% syntax pass rate, LLM4FaaS demonstrates promising feasibility and consistent performance in our evaluation. | BR5: 2.3 Related Work Prior work has integrated LLMs into low-code environments to support human-AI collaboration. | BS5: 2 | BT5: LLM4FaaS: No-Code Application Development using LLMs and FaaS UCC ’25, December 1-4, 2025, Nantes, France Experiment Pylint Score (avg±std) CC (avg±std) MI (avg±std) HALS Effort (median) Baseline3.18±2.34 8.51±6.99 75.13±7.6775.31 Human Developer8.30±1.38 7.06±4.6655.63±15.00272.32 LLM4FaaS6.13±1.85 9.43±7.4278.34±11.8584.26 Open Interpreter7.25±2.06 6.62±6.58 79.73±12.50 24.73 Table 1: Comparison of Code Quality Metrics across Experiments: The table reports the average (avg) and standard deviation (std) of Pylint scores, Cyclomatic Complexity (CC), Maintainability Index (MI), and the median HALS Effort. | BU5: 5 | BV5: Not reported | BW5: Experiments withGPT-4o show that LLM4FaaS can automatically build and deploy code in 71.47% of cases, outperforming a non-FaaS baseline at 43.48% and an existing LLM-based platform at 14.55%, narrowing the gap to human performance at 88.99%. | With a 71.47% semantic and 87.55% syntax pass rate, LLM4FaaS demonstrates promising feasibility and consistent performance in our evaluation. | In the questionnaire, we ask users to describe in natural language how they would instruct a smart home system to automate 4 tasks with increasing complexity. | The average syntactic pass rate for human developers, LLM4FaaS and the baseline are 96.53%, 87.55%, and 88.42%, respectively, while Open Interpreter achieves 31.69%. | BX5: Moderate | BY5: PDF text extracted from 8 pages; sample evidence page: p. 3. | BZ5: . 4.4.1 Impact of FaaS.Results from the baseline and Open Interpreter experiments indicate that leveraging FaaS in LLM4FaaS effectively preserves the syntactic correctness of LLM-generated code. Moreover, the reduced complexity from FaaS programming model allows the LLM to focus on understanding and implementing user intentions rather than boilerplate code for operational concerns, leading to a significantly higher semantic pass rate. 4.4.2 Task Complexity.Our results show that task complexity impacts the semantic pass rate of LLM4FaaS. We consider two possible causes: First, the increased task complexity presents challenges for LLMs, posing more opportunity for failure. Second, increased complexity can also be challenging for users, particularly those with less experience, who must understand and articulate more complex LLM4FaaS: No-Code Application Development using LLMs and FaaS UCC ’25, December 1-4, 2025, Nantes, France Easy Medium Advanced Complex Automation Tasks 0 25 50 75 100 Syntactic Repeat Pass Rate (%) User1 User2 User3 (a) Syntactic repeat pass rate Easy Medium Advanced Complex Automation Tasks 0 25 50 75 100 Semantic Repeat Pass Rate (%) User1 User2 User3 (b) Semantic repeat pass rate Figure 5: Pass rates of ten repetitions of LLM4FaaS with three user answers. Syntactic pass remains stable between repeat LLM invocations (nine or ten of ten correct). For the co... | CA5: Automated extraction should be checked against the PDF for high-impact fields | CB5: on prompting strategies could help LLM4FaaS better handle complex, multi-intent tasks. 4.4.3 Model Selection.We choose GPT-4o as the primary LLM for LLM4FaaS due to its advanced capabilities and strong performance in non-English languages [ 13]. LLM4FaaS exhibits practical performance with GPT-4o, even when handling more complex tasks. Nevertheless, advances in LLMs will likely improve the performance of LLM4FaaS. In future work, we plan to further evaluate our approach with different LLMs, including models specifically trained for software development. 4.4.4 Size of the User Group.In this paper, our evaluation is based on answers from 26 non-technical users. While it would have been desirable to work with a larger user group for our experiments, this was not feasible due to the resulting effort in acquiring additional users and handling their answers which both required significant manual effort. Nevertheless, we believe that our experiments reliably demonstrate the effectiveness o... | CC5: on prompting strategies could help LLM4FaaS better handle complex, multi-intent tasks. 4.4.3 Model Selection.We choose GPT-4o as the primary LLM for LLM4FaaS due to its advanced capabilities and strong performance in non-English languages [ 13]. LLM4FaaS exhibits practical performance with GPT-4o, even when handling more complex tasks. Nevertheless, advances in LLMs will likely improve the performance of LLM4FaaS. In future work, we plan to further evaluate our approach with different LLMs, including models specifically trained for software development. 4.4.4 Size of the User Group.In this paper, our evaluation is based on answers from 26 non-technical users. While it would have been desirable to work with a larger user group for our experiments, this was not feasible due to the resulting effort in acquiring additional users and handling their answers which both required significant manual effort. Nevertheless, we believe that our experiments reliably demonstrate the effectiveness o... | CD5: Beyond academic prototypes, practical notebook-based systems, e.g., Google Colab, Replit, also demonstrate the feasibility of interactive code generation and execution. | CE5: Not reported | CF5: However, given the latency concern and the rate limit errors observed in the Open Interpreter experiment, the feedback loops may inherently introduce throughput bottlenecks due to rate limit policies of LLM services. | CG5: AI_AUTOMATION | CH5: PLATFORM_COMPARISON | CI5: QUALITY_TESTING | CJ5: ENTERPRISE_ADOPTION | CK5: Prototype Evaluation | CL5: Not reported | CM5: =IFERROR(VLOOKUP($A5,Quality_Appraisal!$A:$P,15,FALSE),"") -> 24 | CN5: =IFERROR(VLOOKUP($A5,Quality_Appraisal!$A:$P,16,FALSE),"") -> Strong | CO5: Yes - central | CP5: Findings/Future | CQ5: Experiments withGPT-4o show that LLM4FaaS can automatically build and deploy code in 71.47% of cases, outperforming a non-FaaS baseline at 43.48% and an existing LLM-based platform at 14.55%, narrowing the gap to human performance at 88.99%. | Further analysis of code quality, programming language diversity, latency, and consistency demonstrates a balanced performance in terms of efficiency, maintainability and availability. | With a 71.47% semantic and 87.55% syntax pass rate, LLM4FaaS demon... | CR5: Not reported | CS5: AI and automation | CT5: Experiments withGPT-4o show that LLM4FaaS can automatically build and deploy code in 71.47% of cases, outperforming a non-FaaS baseline at 43.48% and an existing LLM-based platform at 14.55%, narrowing the gap to human performance at 88.99%. | Further analysis of code quality, programming language diversity, latency, and consistency demonstrates a balanced performance in terms of efficiency, maintainability and availability. | With a 71.47% semantic and 87.55% syntax pass rate, LLM4FaaS demon... | CU5: None beyond normal human verification of automated extraction | CV5: Not reported | CW5: Minghe Wang; Tobias Pfandzelter; Trever Schirmer (2025). LLM4FaaS: No-Code Application Development using LLMs and FaaS. ACM Reference Format:; for redistribution. The definitive Version of Record was published in2025 IEEE/ACM; 18th International Conference on Utility and Cloud Computing (UCC ’25), December 1-4,. | CX5: https://doi.org/10.1145/3773274.3774686
A6: P005 | B6: 5.Exploring Influence Factors on LLM Suitability for No-Code.pdf | C6: research paper\5.Exploring Influence Factors on LLM Suitability for No-Code.pdf | D6: Completed | E6: 2026-06-12 | F6: Checked - OK | G6: Reported | H6: 4 | I6: Verify automated title/authors/method/sample/theme coding and exact quote page numbers before publication use. | J6: Not reported | K6: Exploring Influence Factors on LLM Suitability for No-Code Development of End User IoT Applications | L6: Development of End User Applications; Minghe Wang; Technische Universität Berlin; Scalable Software Systems Research | M6: 2025 | N6: Preprint | O6: arXiv:2505.04710v2 [cs.DC] 21 Oct 2025 | P6: Not reported | Q6: Unclear: discipline not explicitly labeled; paper text concerns LCNC/software systems | R6: Large Language Models, No-Code Development Platforms, End User Development 1 | S6: No-Code Development Platforms (NCDPs) empower non-technical end users to build applications tailored to their specific demands without writing code. While NCDPs lower technical barriers, users still requiresometechnical knowledge, e.g., to structure process steps or define event-action rules. Large Language Models (LLMs) offer a promising solution to further reduce technical requirements by supporting natural language interaction and dynamic code generation. By integrating LLM, NCDPs can be more accessible to non-technical users, enabling application development truly without requiringanytechnical expertise. Despite growing interest in LLM-powered NCDPs, a systematic investigation into the factors influencing LLM suitability and performance remains absent. Understanding these factors is critical to effectively leveraging LLMs capabilities and maximizing their impact. In this paper, we investigate key factors influencing the effectiveness of LLMs in supporting end-user application development within NCDPs. By conducting comprehensive experiments, we evaluate the impact of four key factors, i.e., model selection, prompt language, training data background, and an error-informed few-shot setup, on the quality of generated applications. Specifically, we selected a range of LLMs based on their architecture, scale, design focus, and training data, and evaluated them across four real-world smart home automation scenarios implemented on a representative open-source LLM-powered NCDP. Our findings offer practical insights into how LLMs can be effectively integrated into NCDPs, info... | T6: Include | U6: 5 | V6: Core focus | W6: Exploring Influence Factors on LLM Suitability for No-Code Development of End User IoT Applications | X6: AI and automation | Y6: Platform comparison; Scalability; Education and training | Z6: Supports review questions on LCNC adoption, AI automation, methods, benefits, risks, and gaps depending on assigned theme codes. | AA6: Our findings offer practical insights into how LLMs can be effectively integrated into NCDPs, informing both platform design and the selection of suitable LLMs for end-user application development. | This architecture decouples infrastructure handling concerns from function logic generation, which has been shown to enhance the reliability of LLM outputs, making it server as a stable and representative foundation for isolating and examining LLM-specific factors in NCDPs. | Section 3 describes... | AB6: Some work focuses on translating natural language into structured workflows or applications, for example, Cai et al. [ 8] present an LLM-driven low-code approach that generates editable flowcharts from user instructions for iterative refinement; Esashi et al. [14] target FaaS workflow generation to benefit Cloud developers, using a dataset for compositional multi-tool tasks, though excluding execution; and Wang et al. [ 36], our prior work, use GPT-4oto generate serverless functions and deplo... | AC6: Exploring Influence Factors on LLM Suitability for No-Code Development of End User Applications Minghe Wang mw@3s.tu-berlin.de Technische Universität Berlin Scalable Software Systems Research Group Berlin, Germany Alexandra Kapp ak@3s.tu-berlin.de Technische Universität Berlin Scalable Software Systems Research Group Berlin, Germany Trever Schirmer ts@3s.tu-berlin.de Technische Universität Berlin Scalable Software Systems Research Group Berlin, Germany Tobias Pfandzelter tp@3s.tu-berlin.de Te... | AD6: low-code; no-code; end-user development | AE6: Some work adapts LLM-based platforms to particular domains or examining broader impacts, for example, Monteiro et al. [27] propose NoCodeGPT for web application development with rollback mechanisms, Hagel et al. [17] automate the DSL models generation based on technical descriptions, Chen et al. [ 9] introduce a template-bounded no-code automated machine learning (AutoML) framework, and Liu et al. [23] conduct an empirical comparison of traditional low-code programming and an LLM-based approa... | AF6: Large Language Models, No-Code Development Platforms, End User Development 1 | AG6: No-Code Development Platforms (NCDPs) empower non-technical end users to build applications tailored to their specific demands without writing code. While NCDPs lower technical barriers, users still requiresometechnical knowledge, e.g., to structure process steps or define event-action rules. Large Language Models (LLMs) offer a promising solution to further reduce technical requirements by supporting natural language interaction and dynamic code generation. By integrating LLM, NCDPs can be more accessible to non-technical users, enabling application development truly without requiringanytechnical expertise. Despite growing interest in LLM-powered NCDPs, a systematic investigation into the factors influencing LLM suitability and performance remains absent. Understanding these factors is critical to effectively leveraging LLMs capabilities and maximizing their impact. In this paper, we investigate key factors influencing the effectiveness of LLMs in supporting end-user application development within NCDPs. By conducting comprehensive experiments, we evaluate the impact of four key factors, i.e., model selection, prompt language, training data background, and an error-informed few-shot setup, on the quality of generated applications. Specifically, we selected a range of LLMs based on their architecture, scale, design focus, and training data, and evaluated them across four real-world smart home automation scenarios implemented on a representative open-source LLM-powered NCDP. Our findings offer practical insights into how LLMs can be effectively integrated into NCDPs, info... | AH6: Tool/Platform Proposal | AI6: Technical/Engineering | AJ6: Unclear: method not explicitly named; paper appears to propose or describe an artifact | AK6: Not reported | AL6: No Empirical Data | AM6: Not reported | AN6: IoT | AO6: IoT | AP6: Exploring Influence Factors on LLM Suitability for No-Code Development of End User Applications Minghe Wang mw@3s.tu-berlin.de Technische Universität Berlin Scalable Software Systems Research Group Berlin, Germany Alexandra Kapp ak@3s.tu-berlin.de Technische Universität Berlin Scalable Software Systems Research Group Berlin, Germany Trever Schirmer ts@3s.tu-berlin.de Technische Universität Berlin Scalable Software Systems Research Group Berlin... | AQ6: LLM4FaaS | AR6: LLM4FaaS | AS6: Beyond the question of how well LLMs can perform these tasks and what causes their behavior, introducing LLM-based automation for user-oriented platforms raises interesting research questions outside the domain of computer systems research. | AT6: Some work focuses on translating natural language into structured workflows or applications, for example, Cai et al. [ 8] present an LLM-driven low-code approach that generates editable flowcharts from user instructions for iterative refinement; Esashi et al. [14] target FaaS workflow generation to benefit Cloud developers, using a dataset for compositional multi-tool tasks, though excluding execution; and Wang et al. [ 36], our prior work, use GPT-4oto generate serverless functions and deplo... | AU6: Not reported | AV6: Specifically, we selected a range of LLMs based on their architecture, scale, design focus, and training data, and evaluated them across four real-world smart home automation scenarios implemented on a representative open-source LLM-powered NCDP. | AW6: Exploring Influence Factors on LLM Suitability for No-Code Development of End User Applications Minghe Wang mw@3s.tu-berlin.de Technische Universität Berlin Scalable Software Systems Research Group Berlin, Germany Alexandra Kapp ak@3s.tu-berlin.de Technische Universität Berlin Scalable Software Systems Research Group Berlin, Germany Trever Schirmer ts@3s.tu-berlin.de Technische Universität Berlin Scalable Software Systems Research Group Berlin... | AX6: Not reported | AY6: Not reported | AZ6: Wang et al. different demands on LLMs than code generation as part of a professional developer’s toolchain. | BA6: 3.2.1 Model Selection.With the rapid proliferation of LLMs, it is essential to evaluate their feasibility within NCDPs. | The original response is in Chinese, and we provide an English translation for clarity. errors in the generated results, and thesemantic successis defined as a complete (100%) alignment with user requirements. | A CMR of 100% indicates that all GT outputs are fully covered in MO, i.e., achievessemantic success, while lower scores suggest missing or incorrectly generated outputs. | For example, if the light should be turned on and the curtain closed, but only one task is accomplished, this results in 50%semantic accuracy. | BB6: By conducting comprehensive experiments, we evaluate the impact of four key factors, i.e., model selection, prompt language, training data background, and an error-informed few-shot setup, on the quality of generated applications. | BC6: This architecture decouples infrastructure handling concerns from function logic generation, which has been shown to enhance the reliability of LLM outputs, making it server as a stable and representative foundation for isolating and examining LLM-specific factors in NCDPs. | BD6: Our findings offer practical insights into how LLMs can be effectively integrated into NCDPs, informing both platform design and the selection of suitable LLMs for end-user application development. | This architecture decouples infrastructure handling concerns from function logic generation, which has been shown to enhance the reliability of LLM outputs, making it server as a stable and representative foundation for isolating and examining LLM-specific factors in NCDPs. | Section 3 describes the methodology and study design we followed while investigating the impact factors of LLM-powered NCDPs, and Section 4 presents the experiment results and findings. | BE6: Exploring Influence Factors on LLM Suitability for No-Code Development of End User Applications Minghe Wang mw@3s.tu-berlin.de Technische Universität Berlin Scalable Software Systems Research Group Berlin, Germany Alexandra Kapp ak@3s.tu-berlin.de Technische Universität Berlin Scalable Software Systems Research Group Berlin, Germany Trever Schirmer ts@3s.tu-berlin.de Technische Universität Berlin Scalable Software Systems Research Group Berlin... | Large Language Models (LLMs) offer a promising solution to further reduce technical requirements by supporting natural language interaction and dynamic code generation. | BF6: While NCDPs lower technical barriers, users still requiresometechnical knowledge, e.g., to structure process steps or define event-action rules. | Achieving tailored functionality often requires coding knowledge, creating barriers for non-technical users. | BG6: For example, in smart home environments, some users may prefer window blinds that automatically adjust based on sunlight exposure to maintain steady indoor lighting, while others might prioritize wake-up routines synchronized with natural light or security systems that adapt to their daily schedules. | BH6: (1) Simple: a use case which expects a straightforward device control functionality. | BI6: This limitation hinders the reproducibility and scalability of few-shot evaluation across different platforms.Baidu Qianfanhas a strict | 2.4.2 LLM Suitability in other Domains.There exists research examining LLM suitability in diverse technical domains, for example, Li et al. [22] compare GPT models with smaller fine-tuned models for detecting self-admitted technical debt, proposing a hybrid framework to balance precision and recall; Lu et al. [25] investigate distributed training strategies for large Transformer models, analyzing performance-memory trade-offs across model architectures and parallelization methods; Petrukha et al. [29] introduce SwiftEval, a benchmark for ass... | BJ6: While the landscape of LLM-powered NCDPs is rapidly evolving, existing research has primarily focused on the feasibility of LLM integration [8, 9, 15, 17, 36]. | BK6: This architecture decouples infrastructure handling concerns from function logic generation, which has been shown to enhance the reliability of LLM outputs, making it server as a stable and representative foundation for isolating and examining LLM-specific factors in NCDPs. | BL6: Wang et al. different demands on LLMs than code generation as part of a professional developer’s toolchain. | BM6: It can be useful for developers to understand code or for educational purposes, but it is not ideal for NCDPs, where more targeted and functional code generation is required. | BN6: 2.1 Large Language Models LLMs are advanced artificial intelligence models trained on vast amounts of text data to understand, process and generate humanlike responses. | BO6: This approach streamlines the development process, leading to fast deployment, reducing costs, and enabling flexibility [10, 31, 34]. | BP6: These personalized configurations not only enhance convenience and comfort but can also improve energy efficiency, security, and privacy [3, 37]. | BQ6: Our findings offer practical insights into how LLMs can be effectively integrated into NCDPs, informing both platform design and the selection of suitable LLMs for end-user application development. | This architecture decouples infrastructure handling concerns from function logic generation, which has been shown to enhance the reliability of LLM outputs, making it server as a stable and representative foundation for isolating and examining LLM-specific factors in NCDPs. | Section 3 describes the methodology and study design we followed while investigating the impact factors of LLM-powered NCDPs, and Section 4 presents the experiment results and findings. | BR6: 2.1 Large Language Models LLMs are advanced artificial intelligence models trained on vast amounts of text data to understand, process and generate humanlike responses. | BS6: 2 | BT6: Whileleaderboards compare models on general purpose tests regarding [2, 18, 19, 24], e.g., knowledge, reasoning, or code generation, a more detailed comparison is necessary to understand the influence of varying model factors for specific tasks. | BU6: 1 | BV6: Not reported | BW6: 3.2.1 Model Selection.With the rapid proliferation of LLMs, it is essential to evaluate their feasibility within NCDPs. | The original response is in Chinese, and we provide an English translation for clarity. errors in the generated results, and thesemantic successis defined as a complete (100%) alignment with user requirements. | A CMR of 100% indicates that all GT outputs are fully covered in MO, i.e., achievessemantic success, while lower scores suggest missing or incorrectly generated outputs. | For example, if the light should be turned on and the curtain closed, but only one task is accomplished, this results in 50%semantic accuracy. | BX6: Moderate | BY6: PDF text extracted from 23 pages; sample evidence page: Not reported. | BZ6: .According to the experimental results, theGPT-4oand the Chinese LLMs demonstrate a strong performance in terms of syntactic and semantic accuracy. In contrast, other LLMs struggle with semantic accuracy, though the underlying causes differ. (1) LLaMAeither fails to generate a function or simply restructures and rewrites the reference code provided in the prompt. (2) Geminigenerates an excessive amount of unnecessary code snippets irrelevant to user requirements. While some generated functions contain required functionalities, they often lack semantic accuracy. (3) Copilotprimarily generates skeletal or pseudocode structures, offering little functional implementation. Wang et al. 0 20 40 60 80 100 Semantic Accuracy Rate (%) 0 20 40 60 80 100Percent GPT-4o GPT-4o-mini Baidu-Qianfan Ali-Qwen-Max DeepSeek-R1 (a) Easy 0 20 40 60 80 100 Semantic Accuracy Rate (%) 0 20 40 60 80 100Percent GPT-4o GPT-4o-mini Baidu-Qianfan Ali-Qwen-Max DeepSeek-R1 (b) Medium 0 20 40 60 80 100 Semantic Accuracy Rate (%) 0 20 40 60 80 100Percent GPT-4o GPT-4o-mini Baidu-Qianfan Ali-Qwen-Max DeepSeek-R1 (c) Advanced 0 20 40 60 80 100 Semantic Accuracy Rate (%) 0 20 40 60 80 100Percent GPT-4o GPT-4o-mini Baidu-Qianfan Ali-Qwen-Max DeepSeek-R1 (d) Complex Figure 9: Semantic Accuracy Comparison with Chinese Models:GPT-4oalso outperforms the Chinese models in semantic accuracy across tasks of varying diffi... | CA6: Sample/data adequacy could not be verified from parsed text; Research method not explicitly identified | CB6: . 5.1 Model Selection Strategy With the release of a range of diverse LLMs in recent years, new opportunities for NCDP rose. However, it is challenging to maintain an overview over model performances and select the most suitable for the use case at hand. With a vast number of available LLMs, each exhibiting different strengths and weaknesses, choosing the right model requires careful consideration. In this case, we select five LLMs that differ in design intent, optimization strategy, scale, and open-source or proprietary to assess their suitability for NCDPs. According to the experiment results, the general-purpose LLMs with strong capability, such asOpenAImodels, i.e.,GPT-4o andGPT-4o-mini, consistently show strong performance among tasks in different levels of complexity and outperform the other models. This is true even for the LLM designed specific for software engineering tasks, e.g.,Copilot, open-source LLM optimized for efficiency and strong adaptability, e.g.,LLaMA, and LLM... | CC6: . 5.1 Model Selection Strategy With the release of a range of diverse LLMs in recent years, new opportunities for NCDP rose. However, it is challenging to maintain an overview over model performances and select the most suitable for the use case at hand. With a vast number of available LLMs, each exhibiting different strengths and weaknesses, choosing the right model requires careful consideration. In this case, we select five LLMs that differ in design intent, optimization strategy, scale, and open-source or proprietary to assess their suitability for NCDPs. According to the experiment results, the general-purpose LLMs with strong capability, such asOpenAImodels, i.e.,GPT-4o andGPT-4o-mini, consistently show strong performance among tasks in different levels of complexity and outperform the other models. This is true even for the LLM designed specific for software engineering tasks, e.g.,Copilot, open-source LLM optimized for efficiency and strong adaptability, e.g.,LLaMA, and LLM... | CD6: Our findings offer practical insights into how LLMs can be effectively integrated into NCDPs, informing both platform design and the selection of suitable LLMs for end-user application development. | CE6: Not reported | CF6: (1) Simple: a use case which expects a straightforward device control functionality. | CG6: AI_AUTOMATION | CH6: PLATFORM_COMPARISON | CI6: SCALABILITY | CJ6: EDUCATION | CK6: Not reported | CL6: Not reported | CM6: =IFERROR(VLOOKUP($A6,Quality_Appraisal!$A:$P,15,FALSE),"") -> 20 | CN6: =IFERROR(VLOOKUP($A6,Quality_Appraisal!$A:$P,16,FALSE),"") -> Strong | CO6: Yes - central | CP6: Findings/Future | CQ6: Our findings offer practical insights into how LLMs can be effectively integrated into NCDPs, informing both platform design and the selection of suitable LLMs for end-user application development. | This architecture decouples infrastructure handling concerns from function logic generation, which has been shown to enhance the reliability of LLM outputs, making it server as a stable and representative foundation for isolating and examining LLM-specific factors in NCDPs. | Section 3 describes... | CR6: Not reported | CS6: AI and automation | CT6: Our findings offer practical insights into how LLMs can be effectively integrated into NCDPs, informing both platform design and the selection of suitable LLMs for end-user application development. | This architecture decouples infrastructure handling concerns from function logic generation, which has been shown to enhance the reliability of LLM outputs, making it server as a stable and representative foundation for isolating and examining LLM-specific factors in NCDPs. | Section 3 describes... | CU6: sample/data size missing | CV6: Not reported | CW6: Development of End User Applications; Minghe Wang; Technische Universität Berlin; Scalable Software Systems Research (2025). Exploring Influence Factors on LLM Suitability for No-Code Development of End User IoT Applications. arXiv:2505.04710v2 [cs.DC] 21 Oct 2025. | CX6: Not reported
A7: P006 | B7: 6.DMN-Guided Prompting A Framework for Controlling.pdf | C7: research paper\6.DMN-Guided Prompting A Framework for Controlling.pdf | D7: Completed | E7: 2026-06-12 | F7: Checked - OK | G7: Reported | H7: 4 | I7: Verify automated title/authors/method/sample/theme coding and exact quote page numbers before publication use. | J7: Not reported | K7: DMN-Guided Prompting: A Framework for Controlling LLM Behavior | L7: Shaghayegh Abedi1 and Amin Jalali2 | M7: 2023 | N7: Preprint | O7: arXiv:2505.11701v2 [cs.AI] 4 Sep 2025 | P7: SAGE | Q7: Unclear: discipline not explicitly labeled; paper text concerns LCNC/software systems | R7: Large Language Models, Decision Model and Notation, Automated Feedback, Prompt Engineering 1 | S7: . Large Language Models (LLMs) have shown considerable potential in automating decision logic within knowledge-intensive processes. However, their effectiveness largely depends on the strategy and quality of prompting. Since decision logic is typically embedded in prompts, it becomes challenging for end users to modify or refine it. Decision Model and Notation (DMN) offers a standardized graphical approach for defining decision logic in a structured, userfriendly manner. This paper introduces a DMN-guided prompting framework that breaks down complex decision logic into smaller, manageable components, guiding LLMs through structured decision pathways. We implemented the framework in a graduate-level course where students submitted assignments. The assignments and DMN models representing feedback instructions served as inputs to our framework. The instructor evaluated the generated feedback and labeled it for performance assessment. Our approach demonstrated promising results, outperforming chain-of-thought (CoT) prompting in our case study. Students also responded positively to the generated feedback, reporting high levels of perceived usefulness in a survey based on the Technology Acceptance Model. | T7: Maybe | U7: 1 | V7: Not LCNC | W7: DMN-Guided Prompting: A Framework for Controlling LLM Behavior | X7: AI and automation | Y7: Education and training; Governance and control; Scalability | Z7: Supports review questions on LCNC adoption, AI automation, methods, benefits, risks, and gaps depending on assigned theme codes. | AA7: Our approach demonstrated promising results, outperforming chain-of-thought (CoT) prompting in our case study. | These labeled data were used to evaluate the approach, and the results show that DMN-guided prompting outperformed equivalent prompts defined purely using chain-of-thought prompting [20]. | These examples were found to be crucial in avoiding hallucinations, particularly in boundary conditions. - C3 Retrieve Literal Expression: Once a matching decision rule is identified, the LLM re... | AB7: Not reported | AC7: Not reported | AD7: Not reported | AE7: DMN-Guided Prompting: A Framework for Controlling LLM Behavior Shaghayegh Abedi1 and Amin Jalali2 1 Politecnico di Torino, Turin, Italy, s309894@studenti.polito.it 2 Stockholm University, Stockholm, Sweden, aj@dsv.su.se Abstract. | AF7: Large Language Models, Decision Model and Notation, Automated Feedback, Prompt Engineering 1 | AG7: . Large Language Models (LLMs) have shown considerable potential in automating decision logic within knowledge-intensive processes. However, their effectiveness largely depends on the strategy and quality of prompting. Since decision logic is typically embedded in prompts, it becomes challenging for end users to modify or refine it. Decision Model and Notation (DMN) offers a standardized graphical approach for defining decision logic in a structured, userfriendly manner. This paper introduces a DMN-guided prompting framework that breaks down complex decision logic into smaller, manageable components, guiding LLMs through structured decision pathways. We implemented the framework in a graduate-level course where students submitted assignments. The assignments and DMN models representing feedback instructions served as inputs to our framework. The instructor evaluated the generated feedback and labeled it for performance assessment. Our approach demonstrated promising results, outperforming chain-of-thought (CoT) prompting in our case study. Students also responded positively to the generated feedback, reporting high levels of perceived usefulness in a survey based on the Technology Acceptance Model. | AH7: Empirical Study | AI7: Quantitative | AJ7: Survey | AK7: Survey | AL7: Primary Data | AM7: Human participants or experimental tasks | AN7: healthcare | AO7: healthcare | AP7: Since decision logic is typically embedded in prompts, it becomes challenging for end users to modify or refine it. | AQ7: DMN | AR7: DMN | AS7: Not reported | AT7: Because LLMs generate output based on probabilistic patterns learned from large datasets, their responses are susceptible to the wording, structure, and context provided in the prompt. | AU7: Not reported | AV7: These rules align with specific BPR principles and provide pedagogically meaningful evaluation criteria for student submissions. | AW7: Since decision logic is typically embedded in prompts, it becomes challenging for end users to modify or refine it. | AX7: Not reported | AY7: Not reported | AZ7: Students also responded positively to the generated feedback, reporting high levels of perceived usefulness in a survey based on the Technology Acceptance Model. | BA7: Rule 2 (task composition) was correctly implemented by the majority (79%) of the groups, and the framework achieved 86% accuracy in identifying them - closely aligned with the overall accuracy. | For Rule 3 (knock-out), 93% of the groups modeled the principle correctly, and the framework matched this performance with a 93% accuracy rate - exceeding its overall average. | DMN-Guided Prompting 11 In contrast, Rule 5 (task resequencing) was the most challenging for students, with only one group (7%) correctly reordering tasks. | Despite this, the framework successfully identified the intended logic in 93% of the cases. | BB7: The instructor evaluated the generated feedback and labeled it for performance assessment. | BC7: To ensure reliability, the generated feedback was not directly shared with students. | BD7: Our approach demonstrated promising results, outperforming chain-of-thought (CoT) prompting in our case study. | These labeled data were used to evaluate the approach, and the results show that DMN-guided prompting outperformed equivalent prompts defined purely using chain-of-thought prompting [20]. | These examples were found to be crucial in avoiding hallucinations, particularly in boundary conditions. - C3 Retrieve Literal Expression: Once a matching decision rule is identified, the LLM retrieves the corresponding literal expression associated with the outcome. - C4 Return Final Message: The final step ensures that only the decision message (from the literal expression) is returned. | BE7: This approach reduces the dependency on ad hoc changes of prompts, making arXiv:2505.11701v2 [cs.AI] 4 Sep 2025 | This framework offers several key benefits: Modularity: Components can be independently created, reused, or updated, supporting maintainable and scalable prompt design. | BF7: However, their effectiveness largely depends on the strategy and quality of prompting. | However, the effectiveness of LLMs critically depends on the quality of their instructions, also known as prompts. | BG7: If you have any questions or would like further clarification, please feel free to contact us."    privacy terms imprint cookie preferences about give feedback https://demo.bpmn.io/dmn/new 1/1 Fig. | BH7: Hit policy:Loan Approval Rule Unique  > 50000 >= 700 approve > 50000 [650..700[ manual_review - - decline - - Annotations 1 2 3  Then Is Eligible for Loan? string  When salary string And creditScore string  Fig. | BI7: This framework offers several key benefits: Modularity: Components can be independently created, reused, or updated, supporting maintainable and scalable prompt design. | Developing such prompts (commonly known as prompt engineering) is often a trial-and-error process, requiring technical expertise and posing challenges related to transparency, reusability, and maintenance [15, 19]. | BJ7: Not reported | BK7: Acknowledgment: The computations for testing and developing our approach were enabled by resources provided by the National Academic Infrastructure for Supercomputing in Sweden (NAISS), partially funded by the Swedish Research Council through grant agreement no. | BL7: 2 Shaghayegh Abedi and Amin Jalali it easier to understand, modify, and maintain - particularly in settings where clarity, consistency, and collaboration are essential. | BM7: We begin by describing the educational setting, followed by the implementation and evaluation methodology, and conclude with findings concerning system performance and student perceptions. | BN7: Our approach demonstrated promising results, outperforming chain-of-thought (CoT) prompting in our case study. | BO7: These descriptions retain critical control flow and resource semantics, enabling LLMs to interpret process models as standardized textual artifacts. | BP7: However, their effectiveness largely depends on the strategy and quality of prompting. | BQ7: Our approach demonstrated promising results, outperforming chain-of-thought (CoT) prompting in our case study. | These labeled data were used to evaluate the approach, and the results show that DMN-guided prompting outperformed equivalent prompts defined purely using chain-of-thought prompting [20]. | These examples were found to be crucial in avoiding hallucinations, particularly in boundary conditions. - C3 Retrieve Literal Expression: Once a matching decision rule is identified, the LLM retrieves the corresponding literal expression associated with the outcome. - C4 Return Final Message: The final step ensures that only the decision message (from the literal expression) is returned. | BR7: This approach reduces the dependency on ad hoc changes of prompts, making arXiv:2505.11701v2 [cs.AI] 4 Sep 2025 | BS7: 1 | BT7: We implemented the framework in a graduate-level course where students submitted assignments. | BU7: 1 | BV7: Not reported | BW7: Rule 2 (task composition) was correctly implemented by the majority (79%) of the groups, and the framework achieved 86% accuracy in identifying them - closely aligned with the overall accuracy. | For Rule 3 (knock-out), 93% of the groups modeled the principle correctly, and the framework matched this performance with a 93% accuracy rate - exceeding its overall average. | DMN-Guided Prompting 11 In contrast, Rule 5 (task resequencing) was the most challenging for students, with only one group (7%) correctly reordering tasks. | Despite this, the framework successfully identified the intended logic in 93% of the cases. | BX7: Moderate | BY7: PDF text extracted from 15 pages; sample evidence page: Not reported. | BZ7: observed in the study. Finally, Section 5 concludes the paper and introduces future directions. 2 Background 2.1 Decision Model and Notation Decision Model and Notation (DMN) is a standard developed by the Object Management Group (OMG) to represent decision logic in a clear, structured, and interpretable format [1]. It is widely used in business process management to separate decision logic from process flows, enabling organizations to formalize and automate operational decisions transparently. A key advantage of DMN is its accessibility to both business professionals and technical users. It offers graphical and tabular notations that help bridge the gap between informal business rules and executable logic [2, 14]. DMN supports decision modeling using the Decision Requirements Diagram (DRD) [1]. Fig. 1 presents a sample DRD that will serve as a running example throughout this paper to illustrate our approach (for the complete DMN specification, refer to [1]). This diagram specifies the rules for a fictitious loan eligibility process, where the decision is based on the applicant’s Salary and Credit Score, modeled as input data elements. A decision table element, named Loan Approval Rule, encodes the decision logic. The decision output is then passed to a literal expression element, called Loan Approval Result. Literal expressions represent decision logic using textual stateme... | CA7: Sample/data adequacy could not be verified from parsed text | CB7: can expand in several directions. First, exploring how DMN-guided prompting can be adapted for other application domains, such as healthcare or compliance auditing, will help assess its generalizability. Second, combining DMN with retrieval-augmented generation (RAG) may further enhance reasoning grounded in external knowledge. Third, if customized message generation is desired, the LLM can post-process the output messages using a secondary prompt; otherwise, the framework returns only the predefined messages specified in the DMN logic. Fourth, this approach can be complemented by incorporating few-shot learning, where example inputs are used to improve LLM accuracy when interpreting or applying DMN rules. Fifth, other ways of defining DMN rules and alternative strategies for prompt construction can be explored to increase flexibility and expressiveness. Finally, investigating multi-turn interactions and conversational agents powered by DMN-guided LLMs could open new opportunities f... | CC7: can expand in several directions. First, exploring how DMN-guided prompting can be adapted for other application domains, such as healthcare or compliance auditing, will help assess its generalizability. Second, combining DMN with retrieval-augmented generation (RAG) may further enhance reasoning grounded in external knowledge. Third, if customized message generation is desired, the LLM can post-process the output messages using a secondary prompt; otherwise, the framework returns only the predefined messages specified in the DMN logic. Fourth, this approach can be complemented by incorporating few-shot learning, where example inputs are used to improve LLM accuracy when interpreting or applying DMN rules. Fifth, other ways of defining DMN rules and alternative strategies for prompt construction can be explored to increase flexibility and expressiveness. Finally, investigating multi-turn interactions and conversational agents powered by DMN-guided LLMs could open new opportunities f... | CD7: Hit policy:Loan Approval Rule Unique  > 50000 >= 700 approve > 50000 [650..700[ manual_review - - decline - - Annotations 1 2 3  Then Is Eligible for Loan? string  When salary string And creditScore string  Fig. | CE7: Not reported | CF7: Hit policy:Loan Approval Rule Unique  > 50000 >= 700 approve > 50000 [650..700[ manual_review - - decline - - Annotations 1 2 3  Then Is Eligible for Loan? string  When salary string And creditScore string  Fig. | CG7: AI_AUTOMATION | CH7: EDUCATION | CI7: GOVERNANCE | CJ7: SCALABILITY | CK7: Survey | CL7: Not reported | CM7: =IFERROR(VLOOKUP($A7,Quality_Appraisal!$A:$P,15,FALSE),"") -> 18 | CN7: =IFERROR(VLOOKUP($A7,Quality_Appraisal!$A:$P,16,FALSE),"") -> Moderate | CO7: Maybe | CP7: Findings/Future | CQ7: Our approach demonstrated promising results, outperforming chain-of-thought (CoT) prompting in our case study. | These labeled data were used to evaluate the approach, and the results show that DMN-guided prompting outperformed equivalent prompts defined purely using chain-of-thought prompting [20]. | These examples were found to be crucial in avoiding hallucinations, particularly in boundary conditions. - C3 Retrieve Literal Expression: Once a matching decision rule is identified, the LLM re... | CR7: Not reported | CS7: AI and automation | CT7: Our approach demonstrated promising results, outperforming chain-of-thought (CoT) prompting in our case study. | These labeled data were used to evaluate the approach, and the results show that DMN-guided prompting outperformed equivalent prompts defined purely using chain-of-thought prompting [20]. | These examples were found to be crucial in avoiding hallucinations, particularly in boundary conditions. - C3 Retrieve Literal Expression: Once a matching decision rule is identified, the LLM re... | CU7: sample/data size missing | CV7: Not reported | CW7: Shaghayegh Abedi1 and Amin Jalali2 (2023). DMN-Guided Prompting: A Framework for Controlling LLM Behavior. arXiv:2505.11701v2 [cs.AI] 4 Sep 2025. | CX7: Not reported
A8: P007 | B8: 7.Fine-Tune an SLM or Prompt an LLM The Case of Generating.pdf | C8: research paper\7.Fine-Tune an SLM or Prompt an LLM The Case of Generating.pdf | D8: Completed | E8: 2026-06-12 | F8: Checked - OK | G8: Reported | H8: 4 | I8: Verify automated title/authors/method/sample/theme coding and exact quote page numbers before publication use. | J8: Not reported | K8: Fine-Tune an SLM or Prompt an LLM? The Case of Generating Low-Code Workflows | L8: Low-Code Workflows; Orlando Marquez Ayala; ServiceNow; Patrice Bechard | M8: 2023 | N8: Preprint | O8: KDD Workshop ’25, Toronto, Canada; arXiv:2505.24189v2 [cs.LG] 16 Jul 2025; KDD Workshop ’25, August 03-07,2025, Toronto, Canada Orlando Marquez Ayala, Patrice Bechard, Emily Chen, Maggie Baird, and Jingfei Chen | P8: SAGE | Q8: Unclear: discipline not explicitly labeled; paper text concerns LCNC/software systems | R8: Large Language Models, Generative AI, Retrieval-Augmented Generation, Task Decomposition, Workflows 1 | S8: Large Language Models (LLMs) such as GPT-4o can handle a wide range of complex tasks with the right prompt. As per token costs are reduced, the advantages of fine-tuning Small Language Models (SLMs) for real-world applications - faster inference, lower costs - may no longer be clear. In this work, we present evidence that, for domain-specific tasks that require structured outputs, SLMs still have a quality advantage. We compare fine-tuning an SLM against prompting LLMs on the task of generating low-code workflows in JSON form. We observe that while a good prompt can yield reasonable results, fine-tuning improves quality by 10% on average. We also perform systematic error analysis to reveal model limitations. CCS Concepts •Computing methodologies → Natural language processing; Machine learning; •Information systems → Specialized information retrieval; Enterprise information systems. | T8: Include | U8: 5 | V8: Core focus | W8: Fine-Tune an SLM or Prompt an LLM? The Case of Generating Low-Code Workflows | X8: AI and automation | Y8: Platform comparison; Education and training; Limitations and research gaps | Z8: Supports review questions on LCNC adoption, AI automation, methods, benefits, risks, and gaps depending on assigned theme codes. | AA8: We also perform systematic error analysis to reveal model limitations. | We found out that, while prompting an LLM gives reasonable results, we can do better by fine-tuning an SLM. | Our contributions are the following: • We present a case study for how we built an application that generates low-code workflows based on textual user requirements. • We demonstrate that fine-tuning an SLM gives better results than prompting much larger LLMs in this domain-specific task. • We introduce a process... | AB8: Not reported | AC8: Not reported | AD8: low-code | AE8: Not reported | AF8: Large Language Models, Generative AI, Retrieval-Augmented Generation, Task Decomposition, Workflows 1 | AG8: Large Language Models (LLMs) such as GPT-4o can handle a wide range of complex tasks with the right prompt. As per token costs are reduced, the advantages of fine-tuning Small Language Models (SLMs) for real-world applications - faster inference, lower costs - may no longer be clear. In this work, we present evidence that, for domain-specific tasks that require structured outputs, SLMs still have a quality advantage. We compare fine-tuning an SLM against prompting LLMs on the task of generating low-code workflows in JSON form. We observe that while a good prompt can yield reasonable results, fine-tuning improves quality by 10% on average. We also perform systematic error analysis to reveal model limitations. CCS Concepts •Computing methodologies → Natural language processing; Machine learning; •Information systems → Specialized information retrieval; Enterprise information systems. | AH8: Empirical Study | AI8: Qualitative | AJ8: Case Study | AK8: Case Study | AL8: Primary Data | AM8: Not reported | AN8: Not reported | AO8: Not reported | AP8: Some of the challenges in this task are: • Every step must exist in the system environment; they vary by installation and users can add custom steps. • Workflow structure must follow a set of well-defined rules, using concepts such as conditions (e.g., IF) and loops (e.g., FOREACH). • Every step generates outputs of data types such as integer or boolean, which can be used in subsequent steps. • Steps have inputs that can refer to database tabl... | AQ8: Not reported | AR8: low-code | AS8: Not reported | AT8: For example, the Look Up Incident Records step in Figure 1 matches rows in the incident table where the column assigned_to has the same value as the user record from the trigger step. arXiv:2505.24189v2 [cs.LG] 16 Jul 2025 | AU8: Not reported | AV8: After discarding those too short or too long, we selected 1,512 workflows. | AW8: Some of the challenges in this task are: • Every step must exist in the system environment; they vary by installation and users can add custom steps. • Workflow structure must follow a set of well-defined rules, using concepts such as conditions (e.g., IF) and loops (e.g., FOREACH). • Every step generates outputs of data types such as integer or boolean, which can be used in subsequent steps. • Steps have inputs that can refer to database tabl... | AX8: Not reported | AY8: Not reported | AZ8: We also created a special dataset by inviting expert enterprise users to interact with the tool and collecting data generated from their usage. | BA8: We observe that while a good prompt can yield reasonable results, fine-tuning improves quality by 10% on average. | Dataset # createFlow # populateInputs Internal 1,512 4,709 Synthetic 766 2,310 TEST 108 367 OOD 1,072 4,958 4.2 Models For SLMs, we considered several models such as StarCoderBase-7B [17] and Llama-3.1-8B [13], but we chose Mistral-Nemo-12B-Base [20] because this model architecture is well-supported and optimized in our enterprise system. | This gap is 7.2% on TEST but 12.4% on OOD, around 10% if we average the two. | Nevertheless, we see that the improvement is only a maximum of 4%, suggesting that most errors are model errors. | BB8: We also perform systematic error analysis to reveal model limitations. | BC8: Not reported | BD8: We also perform systematic error analysis to reveal model limitations. | We found out that, while prompting an LLM gives reasonable results, we can do better by fine-tuning an SLM. | Our contributions are the following: • We present a case study for how we built an application that generates low-code workflows based on textual user requirements. • We demonstrate that fine-tuning an SLM gives better results than prompting much larger LLMs in this domain-specific task. • We introduce a process to conduct systematic error analysis that reveals model limitations and complements our metrics. | BE8: As per token costs are reduced, the advantages of fine-tuning Small Language Models (SLMs) for real-world applications - faster inference, lower costs - may no longer be clear. | We observe that while a good prompt can yield reasonable results, fine-tuning improves quality by 10% on average. | BF8: We also perform systematic error analysis to reveal model limitations. | Some of the challenges in this task are: • Every step must exist in the system environment; they vary by installation and users can add custom steps. • Workflow structure must follow a set of well-defined rules, using concepts such as conditions (e.g., IF) and loops (e.g., FOREACH). • Every step generates outputs of data types such as integer or boolean, which can be used in subsequent steps. • Steps have inputs that can refer to database tabl... | BG8: Not reported | BH8: Not reported | BI8: In various industry-specific settings, specialized models have demonstrated superior performance over state-of-the-art general-domain LLMs [6, 25, 30]. | It makes the process less time-consuming due to its reusability and extensibility. | BJ8: As per token costs are reduced, the advantages of fine-tuning Small Language Models (SLMs) for real-world applications - faster inference, lower costs - may no longer be clear. | BK8: Not reported | BL8: Not reported | BM8: Our approach was to create a small yet representative training dataset for the sub-tasks comprising Flow Generation and fine-tune Mistral-Nemo-12B-Base [20]. | BN8: The Case of Generating Low-Code Workflows Orlando Marquez Ayala ServiceNow orlando.marquez@servicenow.com Patrice Bechard ServiceNow patrice.bechard@servicenow.com Emily Chen ServiceNow emily.chen@servicenow.com Maggie Baird ServiceNow maggie.baird@servicenow.com Jingfei Chen ServiceNow jingfei.chen@servicenow.com Abstract Large Language Models (LLMs) such as GPT-4o can handle a wide range of complex tasks with the right prompt. | BO8: As per token costs are reduced, the advantages of fine-tuning Small Language Models (SLMs) for real-world applications - faster inference, lower costs - may no longer be clear. | BP8: Although prompting state-of-the-art models such as GPT-4o [15], Gemini 2.0 Flash [12], or Claude 3.5 Sonnet [1] generally suffice for traditional tasks like question-answering or summarization [9], it is not always the case on domain-specific tasks [24]. | BQ8: We also perform systematic error analysis to reveal model limitations. | We found out that, while prompting an LLM gives reasonable results, we can do better by fine-tuning an SLM. | Our contributions are the following: • We present a case study for how we built an application that generates low-code workflows based on textual user requirements. • We demonstrate that fine-tuning an SLM gives better results than prompting much larger LLMs in this domain-specific task. • We introduce a process to conduct systematic error analysis that reveals model limitations and complements our metrics. | BR8: Keywords Large Language Models, Generative AI, Retrieval-Augmented Generation, Task Decomposition, Workflows 1 Introduction Generative AI is pushing the boundaries of AI-based software. | BS8: 1 | BT8: Our last quantitative comparison helps us determine whether suboptimal RAG is primarily responsible for errors. | BU8: 4 | BV8: Not reported | BW8: We observe that while a good prompt can yield reasonable results, fine-tuning improves quality by 10% on average. | Dataset # createFlow # populateInputs Internal 1,512 4,709 Synthetic 766 2,310 TEST 108 367 OOD 1,072 4,958 4.2 Models For SLMs, we considered several models such as StarCoderBase-7B [17] and Llama-3.1-8B [13], but we chose Mistral-Nemo-12B-Base [20] because this model architecture is well-supported and optimized in our enterprise system. | This gap is 7.2% on TEST but 12.4% on OOD, around 10% if we average the two. | Nevertheless, we see that the improvement is only a maximum of 4%, suggesting that most errors are model errors. | BX8: Moderate | BY8: PDF text extracted from 8 pages; sample evidence page: Not reported. | BZ8: . CCS Concepts •Computing methodologies → Natural language processing; Machine learning; •Information systems → Specialized information retrieval; Enterprise information systems. Keywords Large Language Models, Generative AI, Retrieval-Augmented Generation, Task Decomposition, Workflows 1 Introduction Generative AI is pushing the boundaries of AI-based software. As Large Language Models (LLMs) become more capable, they have become an integral part of the software stack. Although prompting state-of-the-art models such as GPT-4o [15], Gemini 2.0 Flash [12], or Claude 3.5 Sonnet [1] generally suffice for traditional tasks like question-answering or summarization [9], it is not always the case on domain-specific tasks [24]. While building Flow Generation, an application that generates low-code workflows based on textual user requirements, we explored whether fine-tuning a language model was necessary to achieve the desired software quality. To reduce infrastructure needs, we only considered Small Language Models (SLMs), having less than 15 billion parameters. Enterprise workflows are a common way to automate repetitive yet complex processes. They are represented as a series of steps that are executed under certain conditions to fulfill specific goals. While low-code workflows tend to be built in easy-to-use interfaces, creating them still requires expert knowledge of the enterpr... | CA8: Sample/data adequacy could not be verified from parsed text | CB8: . We address the third drawback by computing the percentage of generated examples with at least one such structure error. While the most complete metric is FlowSim of outline and inputs , we also report FlowSim of outline, and the percentage of examples with structure errors. 5 Results Figure 4 shows the results for our fine-tuned SLM and all other LLMs on the small TEST and the larger OOD datasets. MistralNemo-12B-Instruct performs poorly across the board confirming that SLMs require workflow in-domain training data. LLMs of the "mini" sort, even o3-mini with medium reasoning, also do not perform well. When we prompt larger LLMs, we see competitive results, especially with Gemini-2.0-Flash and GPT-4o. As generating the outline is a simpler task, we see a larger gap between our fine-tuned SLM and these models when we generate the complete workflow (outline and inputs). This gap is 7.2% on TEST but 12.4% on OOD, around 10% if we average the two. All models perform worse when the requ... | CC8: . We address the third drawback by computing the percentage of generated examples with at least one such structure error. While the most complete metric is FlowSim of outline and inputs , we also report FlowSim of outline, and the percentage of examples with structure errors. 5 Results Figure 4 shows the results for our fine-tuned SLM and all other LLMs on the small TEST and the larger OOD datasets. MistralNemo-12B-Instruct performs poorly across the board confirming that SLMs require workflow in-domain training data. LLMs of the "mini" sort, even o3-mini with medium reasoning, also do not perform well. When we prompt larger LLMs, we see competitive results, especially with Gemini-2.0-Flash and GPT-4o. As generating the outline is a simpler task, we see a larger gap between our fine-tuned SLM and these models when we generate the complete workflow (outline and inputs). This gap is 7.2% on TEST but 12.4% on OOD, around 10% if we average the two. All models perform worse when the requ... | CD8: Not reported | CE8: Not reported | CF8: Not reported | CG8: AI_AUTOMATION | CH8: PLATFORM_COMPARISON | CI8: EDUCATION | CJ8: LIMITATIONS_GAPS | CK8: Case Study | CL8: Not reported | CM8: =IFERROR(VLOOKUP($A8,Quality_Appraisal!$A:$P,15,FALSE),"") -> 20 | CN8: =IFERROR(VLOOKUP($A8,Quality_Appraisal!$A:$P,16,FALSE),"") -> Strong | CO8: Yes - central | CP8: Findings/Future | CQ8: We also perform systematic error analysis to reveal model limitations. | We found out that, while prompting an LLM gives reasonable results, we can do better by fine-tuning an SLM. | Our contributions are the following: • We present a case study for how we built an application that generates low-code workflows based on textual user requirements. • We demonstrate that fine-tuning an SLM gives better results than prompting much larger LLMs in this domain-specific task. • We introduce a process... | CR8: Not reported | CS8: AI and automation | CT8: We also perform systematic error analysis to reveal model limitations. | We found out that, while prompting an LLM gives reasonable results, we can do better by fine-tuning an SLM. | Our contributions are the following: • We present a case study for how we built an application that generates low-code workflows based on textual user requirements. • We demonstrate that fine-tuning an SLM gives better results than prompting much larger LLMs in this domain-specific task. • We introduce a process... | CU8: sample/data size missing | CV8: Not reported | CW8: Low-Code Workflows; Orlando Marquez Ayala; ServiceNow; Patrice Bechard (2023). Fine-Tune an SLM or Prompt an LLM? The Case of Generating Low-Code Workflows. KDD Workshop ’25, Toronto, Canada; arXiv:2505.24189v2 [cs.LG] 16 Jul 2025; KDD Workshop ’25, August 03-07,2025, Toronto, Canada Orlando Marquez Ayala, Patrice Bechard, Emily Chen, Maggie Baird, and Jingfei Chen. | CX8: Not reported
A9: P008 | B9: 8.NoCode-bench A Benchmark for Evaluating Natural.pdf | C9: research paper\8.NoCode-bench A Benchmark for Evaluating Natural.pdf | D9: Completed | E9: 2026-06-12 | F9: Checked - OK | G9: Reported | H9: 4 | I9: Verify automated title/authors/method/sample/theme coding and exact quote page numbers before publication use. | J9: Not reported | K9: NoCode-bench: A Benchmark for Evaluating Natural Language-Driven Feature Addition | L9: Language-Driven Feature Addition; Le Deng∗; The State Key Laboratory of; Blockchain and Data Security, | M9: 2023 | N9: Preprint | O9: arXiv:2507.18130v3 [cs.SE] 18 Aug 2025 | P9: Not reported | Q9: Unclear: discipline not explicitly labeled; paper text concerns LCNC/software systems | R9: Not reported | S9: Natural language-driven no-code development aims to enable users to specify software functionality through natural language (NL) without directly editing source code, holding the promise for democratizing software development and increasing productivity. Large language models (LLMs) have demonstrated their great potential in realizing this development paradigm. As software documentation serves as an authoritative NL specification of software functionality, we envision a natural and promising no-code development scenario where users or developers update documentation to specify new features, and LLMs automatically infer and perform the corresponding code changes. To advance no-code development, this work introduces NoCode-bench, a benchmark designed to evaluate LLMs on real-world NL-driven feature addition tasks. NoCode-bench consists of 634 tasks across 10 projects involving about 114k code changes in total, each of which pairs a user-facing documentation change and the corresponding code implementation that can be validated against developer-written test cases. It is constructed through a five-phase pipeline starting from release notes, offering broad coverage and simulating real-world development scenarios. To facilitate lightweight and reliable evaluation under limited resources, we further curate a human-validated subset named NoCode-bench Verified. It covers 114 high-quality instances across projects, where the task clarity and evaluation validity are manually verified. We use NoCode-bench to assess a range of state-of-the-art LLMs. Experimental results show that de... | T9: Include | U9: 5 | V9: Core focus | W9: NoCode-bench: A Benchmark for Evaluating Natural Language-Driven Feature Addition | X9: Platform comparison | Y9: Quality assurance and testing; AI and automation; Definitions and conceptual boundaries | Z9: Supports review questions on LCNC adoption, AI automation, methods, benefits, risks, and gaps depending on assigned theme codes. | AA9: Large language models (LLMs) have demonstrated their great potential in realizing this development paradigm. | Experimental results show that despite significant token consumption, the best task success rate remains as low as 28.07%. | In addition, our analysis reveals that LLMs face key challenges in cross-file editing, comprehensively understanding the codebase structure, and tool calling. | AB9: Not reported | AC9: NoCode-bench: A Benchmark for Evaluating Natural Language-Driven Feature Addition Le Deng∗ The State Key Laboratory of Blockchain and Data Security, Zhejiang University Hangzhou, China dengle@zju.edu.cn Zhonghao Jiang∗ The State Key Laboratory of Blockchain and Data Security, Zhejiang University Hangzhou, China zhonghao.j@zju.edu.cn Jialun Cao The Hong Kong University of Science and Technology Hong Kong, China jialuncao@ust.hk Michael Pradel University of Stuttgart Stuttgart, Germany michael@... | AD9: no-code | AE9: We leverage NoCodebench Verified to systematically evaluate a range of state-of-the-art LLMs with the Agentless and OpenHands frameworks. | AF9: no-code | AG9: Natural language-driven no-code development aims to enable users to specify software functionality through natural language (NL) without directly editing source code, holding the promise for democratizing software development and increasing productivity. Large language models (LLMs) have demonstrated their great potential in realizing this development paradigm. As software documentation serves as an authoritative NL specification of software functionality, we envision a natural and promising no-code development scenario where users or developers update documentation to specify new features, and LLMs automatically infer and perform the corresponding code changes. To advance no-code development, this work introduces NoCode-bench, a benchmark designed to evaluate LLMs on real-world NL-driven feature addition tasks. NoCode-bench consists of 634 tasks across 10 projects involving about 114k code changes in total, each of which pairs a user-facing documentation change and the corresponding code implementation that can be validated against developer-written test cases. It is constructed through a five-phase pipeline starting from release notes, offering broad coverage and simulating real-world development scenarios. To facilitate lightweight and reliable evaluation under limited resources, we further curate a human-validated subset named NoCode-bench Verified. It covers 114 high-quality instances across projects, where the task clarity and evaluation validity are manually verified. We use NoCode-bench to assess a range of state-of-the-art LLMs. Experimental results show that de... | AH9: Tool/Platform Proposal | AI9: Technical/Engineering | AJ9: Benchmarking | AK9: Benchmarking | AL9: Primary Data | AM9: Prototype/tool/platform or benchmark tasks | AN9: localization | AO9: localization | AP9: NoCode-bench: A Benchmark for Evaluating Natural Language-Driven Feature Addition Le Deng∗ The State Key Laboratory of Blockchain and Data Security, Zhejiang University Hangzhou, China dengle@zju.edu.cn Zhonghao Jiang∗ The State Key Laboratory of Blockchain and Data Security, Zhejiang University Hangzhou, China zhonghao.j@zju.edu.cn Jialun Cao The Hong Kong University of Science and Technology Hong Kong, China jialuncao@ust.hk Michael Pradel U... | AQ9: NoCode-bench | AR9: NoCode-bench | AS9: 3 EXPERIMENTAL SETUP 3.1 Research Questions We evaluate the performance of state-of-the-art (SOTA) LLMs on no-code feature addition with NoCode-bench. | Specifically, we aim to address the following research questions (RQs): • RQ1: What are the characteristics of tasks in NoCode-bench compared to SWE-bench? • RQ2: How do state-of-the-art LLM-based techniques perform on NoCode-bench Verified? • RQ3: How do state-of-the-art LLM-based techniques perform on NoCode-bench Full? • RQ4: What are the primary reasons for LLM failures on NoCodebench? | 4 RESULTS 4.1 RQ1: Characteristics & Challenges To better understand the unique characteristics and challenges posed by our benchmark, we analyze and compare the distribution of instances in NoCode-bench and SWE-bench across dimensions related to input complexity, localization difficulty, and editing difficulty as shown in Figure 3. | AT9: NoCode-bench: A Benchmark for Evaluating Natural Language-Driven Feature Addition Le Deng∗ The State Key Laboratory of Blockchain and Data Security, Zhejiang University Hangzhou, China dengle@zju.edu.cn Zhonghao Jiang∗ The State Key Laboratory of Blockchain and Data Security, Zhejiang University Hangzhou, China zhonghao.j@zju.edu.cn Jialun Cao The Hong Kong University of Science and Technology Hong Kong, China jialuncao@ust.hk Michael Pradel University of Stuttgart Stuttgart, Germany michael@... | AU9: NoCode-bench consists of 634 tasks across 10 projects involving about 114k code changes in total, each of which pairs a user-facing documentation change and the corresponding code implementation that can be validated against developer-written test cases. | AV9: As shown in Figure 2, we begin with carefully selected projects (Phase 1), then progressively identify, filter, and collect instances (Phase 2), reconstruct their development environments (Phase 3), filter instances based on execution (Phase 4), and finally refine the task input (Phase 5). | AW9: NoCode-bench: A Benchmark for Evaluating Natural Language-Driven Feature Addition Le Deng∗ The State Key Laboratory of Blockchain and Data Security, Zhejiang University Hangzhou, China dengle@zju.edu.cn Zhonghao Jiang∗ The State Key Laboratory of Blockchain and Data Security, Zhejiang University Hangzhou, China zhonghao.j@zju.edu.cn Jialun Cao The Hong Kong University of Science and Technology Hong Kong, China jialuncao@ust.hk Michael Pradel U... | AX9: Not reported | AY9: Not reported | AZ9: NoCode-bench: A Benchmark for Evaluating Natural Language-Driven Feature Addition Le Deng∗ The State Key Laboratory of Blockchain and Data Security, Zhejiang University Hangzhou, China dengle@zju.edu.cn Zhonghao Jiang∗ The State Key Laboratory of Blockchain and Data Security, Zhejiang University Hangzhou, China zhonghao.j@zju.edu.cn Jialun Cao The Hong Kong University of Science and Technology Hong Kong, China jialuncao@ust.hk Michael Pradel University of Stuttgart Stuttgart, Germany michael@... | BA9: NoCode-bench consists of 634 tasks across 10 projects involving about 114k code changes in total, each of which pairs a user-facing documentation change and the corresponding code implementation that can be validated against developer-written test cases. | Experimental results show that despite significant token consumption, the best task success rate remains as low as 28.07%. | For example, prior work [13, 26] has shown that approximately 60% of overall software development costs are allocated to maintenance activities, with feature addition accounting for around 60% of these maintenance efforts. | For example, only 7.3% of the tasks in SWE-bench involve enhancement tasks like feature additions. | BB9: NoCode-bench: A Benchmark for Evaluating Natural Language-Driven Feature Addition Le Deng∗ The State Key Laboratory of Blockchain and Data Security, Zhejiang University Hangzhou, China dengle@zju.edu.cn Zhonghao Jiang∗ The State Key Laboratory of Blockchain and Data Security, Zhejiang University Hangzhou, China zhonghao.j@zju.edu.cn Jialun Cao The Hong Kong University of Science and Technology Hong Kong, China jialuncao@ust.hk Michael Pradel University of Stuttgart Stuttgart, Germany michael@... | BC9: It covers 114 high-quality instances across projects, where the task clarity and evaluation validity are manually verified. | BD9: Large language models (LLMs) have demonstrated their great potential in realizing this development paradigm. | Experimental results show that despite significant token consumption, the best task success rate remains as low as 28.07%. | In addition, our analysis reveals that LLMs face key challenges in cross-file editing, comprehensively understanding the codebase structure, and tool calling. | BE9: Prior work has shown that no-code development holds promise for democratizing software development and significantly increasing productivity [27, 31]. | To understand and further improve the performance of LLMs in NLdriven no-code development, we need high-quality benchmarks where the instances take NL specifications as input and can simulate real-world development tasks. | BF9: In addition, our analysis reveals that LLMs face key challenges in cross-file editing, comprehensively understanding the codebase structure, and tool calling. | NoCode-bench formulates a new challenge and paves the way for future progress in NL-driven no-code software development. ∗Equal contribution. † Corresponding Author. | BG9: NoCode-bench: A Benchmark for Evaluating Natural Language-Driven Feature Addition Le Deng∗ The State Key Laboratory of Blockchain and Data Security, Zhejiang University Hangzhou, China dengle@zju.edu.cn Zhonghao Jiang∗ The State Key Laboratory of Blockchain and Data Security, Zhejiang University Hangzhou, China zhonghao.j@zju.edu.cn Jialun Cao The Hong Kong University of Science and Technology Hong Kong, China jialuncao@ust.hk Michael Pradel University of Stuttgart Stuttgart, Germany michael@binaervarianz.de Zhongxin Liu† The State Key Labor... | BH9: In contrast, NoCode-bench Verified is a high-quality and more reliable subset, enabling faster and more controlled evaluation of LLMs’ ability to solve no-code feature addition tasks. | BI9: SWE-bench’s per-instance Docker approach incurs significant storage overhead and is less scalable when instances share highly similar environments [ 40]. | For example, prior work [13, 26] has shown that approximately 60% of overall software development costs are allocated to maintenance activities, with feature addition accounting for around 60% of these maintenance efforts. | BJ9: In contrast, NoCode-bench Verified is a high-quality and more reliable subset, enabling faster and more controlled evaluation of LLMs’ ability to solve no-code feature addition tasks. | BK9: This phase ensures that each instance is equipped with a clean and functional containerized environment, establishing a reliable foundation for subsequent testing and analysis. | BL9: Not reported | BM9: As these models provide a diverse spectrum in terms of size and training paradigms, we can explore how different architectures and capabilities impact the performance on no-code feature addition tasks. | BN9: NoCode-bench: A Benchmark for Evaluating Natural Language-Driven Feature Addition Le Deng∗ The State Key Laboratory of Blockchain and Data Security, Zhejiang University Hangzhou, China dengle@zju.edu.cn Zhonghao Jiang∗ The State Key Laboratory of Blockchain and Data Security, Zhejiang University Hangzhou, China zhonghao.j@zju.edu.cn Jialun Cao The Hong Kong University of Science and Technology Hong Kong, China jialuncao@ust.hk Michael Pradel University of Stuttgart Stuttgart, Germany michael@binaervarianz.de Zhongxin Liu† The State Key Labor... | BO9: For example, prior work [13, 26] has shown that approximately 60% of overall software development costs are allocated to maintenance activities, with feature addition accounting for around 60% of these maintenance efforts. | BP9: However, software documentation can range from dozens to thousands of pages, and software projects often consist of tens or hundreds of thousands of lines of code, making such a benchmark too challenging to sensitively measure the progress in this field. | BQ9: Large language models (LLMs) have demonstrated their great potential in realizing this development paradigm. | Experimental results show that despite significant token consumption, the best task success rate remains as low as 28.07%. | In addition, our analysis reveals that LLMs face key challenges in cross-file editing, comprehensively understanding the codebase structure, and tool calling. | BR9: Figure 3: Comparison of golden patch distributions between NoCode-bench and SWE-bench along dimensions related to localization and editing difficulty. - Micro-level FV (FV-Micro): The overall ratio of passed F2P tests to the total number of F2P tests across all instances: FV-Micro = Í𝑁 𝑖=1 #Passed𝑖Í𝑁 𝑖=1 #Total𝑖 , where #Passed𝑖 and #Total𝑖 denote the number of passed and total F2P tests for instance 𝑖, respectively. - Macro-level FV (FV-Macro):The average F2P pass rate across instances: FV-Macro = 1 𝑁 Í𝑁 𝑖=1 #Passed𝑖 #Total𝑖 , where 𝑁 is the total number of instances. | BS9: 7 | BT9: This phase ensures that each instance is equipped with a clean and functional containerized environment, establishing a reliable foundation for subsequent testing and analysis. | BU9: 4 | BV9: Not reported | BW9: NoCode-bench consists of 634 tasks across 10 projects involving about 114k code changes in total, each of which pairs a user-facing documentation change and the corresponding code implementation that can be validated against developer-written test cases. | Experimental results show that despite significant token consumption, the best task success rate remains as low as 28.07%. | For example, prior work [13, 26] has shown that approximately 60% of overall software development costs are allocated to maintenance activities, with feature addition accounting for around 60% of these maintenance efforts. | For example, only 7.3% of the tasks in SWE-bench involve enhancement tasks like feature additions. | BX9: Strong | BY9: PDF text extracted from 12 pages; sample evidence page: p. 1. | BZ9: . Considering the better performance of Agentless, we Table 5: Performance comparison across different LLMs on NoCode-bench Full with Agentless. Model Success% Applied% RT% FV-Micro FV-Macro File% #Token Qwen3-235B6.62% 99.37% 75.24% 10.78% 15.77% 39.46% 0.19M GPT-4o 9.31% 97.00% 71.14% 8.68% 17.81% 43.58% 0.11M DeepSeek-v311.83% 99.84% 77.44% 16.02% 24.09% 47.48%0.31M DeepSeek-R1 14.83%95.90% 79.34% 10.53% 25.78% 44.89% 0.57M Average 10.65% 98.03% 75.79% 11.50% 20.86% 43.85% 0.30M use it as the scaffold to evaluate the remaining four models on NoCode-bench Full, and report the results in Table 5. We find that all four models show decreased performance on NoCode-bench Full compared to NoCode-bench Verified. Specifically, the average success rate of the four used models drops from 18.20% to 10.65%, and the accuracy of modified files drops from 49.49% to 43.85%. We further investigate the causes of this phenomenon. Since NoCode-bench Full is a large-scale dataset involving more extensive file modifications and more complex code changes, it presents a diverse range of challenges. In addition, because NoCodebench Full is unverified, it contains some noise, including unclear documentation changes or low-coverage regression tests, which make it more representative of real-world, no-code feature addition tasks, but harder for LLMs to solve. In contrast, NoCode-bench Verified is a h... | CA9: Automated extraction should be checked against the PDF for high-impact fields | CB9: . Considering the better performance of Agentless, we Table 5: Performance comparison across different LLMs on NoCode-bench Full with Agentless. Model Success% Applied% RT% FV-Micro FV-Macro File% #Token Qwen3-235B6.62% 99.37% 75.24% 10.78% 15.77% 39.46% 0.19M GPT-4o 9.31% 97.00% 71.14% 8.68% 17.81% 43.58% 0.11M DeepSeek-v311.83% 99.84% 77.44% 16.02% 24.09% 47.48%0.31M DeepSeek-R1 14.83%95.90% 79.34% 10.53% 25.78% 44.89% 0.57M Average 10.65% 98.03% 75.79% 11.50% 20.86% 43.85% 0.30M use it as the scaffold to evaluate the remaining four models on NoCode-bench Full, and report the results in Table 5. We find that all four models show decreased performance on NoCode-bench Full compared to NoCode-bench Verified. Specifically, the average success rate of the four used models drops from 18.20% to 10.65%, and the accuracy of modified files drops from 49.49% to 43.85%. We further investigate the causes of this phenomenon. Since NoCode-bench Full is a large-scale dataset involving more extens... | CC9: . Considering the better performance of Agentless, we Table 5: Performance comparison across different LLMs on NoCode-bench Full with Agentless. Model Success% Applied% RT% FV-Micro FV-Macro File% #Token Qwen3-235B6.62% 99.37% 75.24% 10.78% 15.77% 39.46% 0.19M GPT-4o 9.31% 97.00% 71.14% 8.68% 17.81% 43.58% 0.11M DeepSeek-v311.83% 99.84% 77.44% 16.02% 24.09% 47.48%0.31M DeepSeek-R1 14.83%95.90% 79.34% 10.53% 25.78% 44.89% 0.57M Average 10.65% 98.03% 75.79% 11.50% 20.86% 43.85% 0.30M use it as the scaffold to evaluate the remaining four models on NoCode-bench Full, and report the results in Table 5. We find that all four models show decreased performance on NoCode-bench Full compared to NoCode-bench Verified. Specifically, the average success rate of the four used models drops from 18.20% to 10.65%, and the accuracy of modified files drops from 49.49% to 43.85%. We further investigate the causes of this phenomenon. Since NoCode-bench Full is a large-scale dataset involving more extens... | CD9: Not reported | CE9: Not reported | CF9: In contrast, NoCode-bench Verified is a high-quality and more reliable subset, enabling faster and more controlled evaluation of LLMs’ ability to solve no-code feature addition tasks. | CG9: PLATFORM_COMPARISON | CH9: QUALITY_TESTING | CI9: AI_AUTOMATION | CJ9: LCNC_DEF | CK9: Benchmarking | CL9: Not reported | CM9: =IFERROR(VLOOKUP($A9,Quality_Appraisal!$A:$P,15,FALSE),"") -> 24 | CN9: =IFERROR(VLOOKUP($A9,Quality_Appraisal!$A:$P,16,FALSE),"") -> Strong | CO9: Yes - central | CP9: Findings | CQ9: Large language models (LLMs) have demonstrated their great potential in realizing this development paradigm. | Experimental results show that despite significant token consumption, the best task success rate remains as low as 28.07%. | In addition, our analysis reveals that LLMs face key challenges in cross-file editing, comprehensively understanding the codebase structure, and tool calling. | CR9: Not reported | CS9: Platform comparison | CT9: Large language models (LLMs) have demonstrated their great potential in realizing this development paradigm. | Experimental results show that despite significant token consumption, the best task success rate remains as low as 28.07%. | In addition, our analysis reveals that LLMs face key challenges in cross-file editing, comprehensively understanding the codebase structure, and tool calling. | CU9: None beyond normal human verification of automated extraction | CV9: Not reported | CW9: Language-Driven Feature Addition; Le Deng∗; The State Key Laboratory of; Blockchain and Data Security, (2023). NoCode-bench: A Benchmark for Evaluating Natural Language-Driven Feature Addition. arXiv:2507.18130v3 [cs.SE] 18 Aug 2025. | CX9: Not reported
A10: P009 | B10: 9.Review of Tools for Zero-Code LLM Based.pdf | C10: research paper\9.Review of Tools for Zero-Code LLM Based.pdf | D10: Completed | E10: 2026-06-12 | F10: Checked - OK | G10: Reported | H10: 4 | I10: Verify automated title/authors/method/sample/theme coding and exact quote page numbers before publication use. | J10: Not reported | K10: Review of Tools for Zero-Code LLM Based Application Development | L10: Application Development; Priyaranjan Pattnayak1 and Hussain Bohra 2 | M10: 2025 | N10: Preprint | O10: arXiv:2510.19747v1 [cs.SE] 22 Oct 2025 | P10: Not reported | Q10: Unclear: discipline not explicitly labeled; paper text concerns LCNC/software systems | R10: Large Language Models, Citation Generation, Retrieval-Augmented Generation, AI Ethics, Multimodal LLMs, Evaluation Metrics. 1 | S10: .Large Language Models (LLMs) are transforming software creation by enabling zero-code development platforms. This survey reviews recent platforms that let users build applications without writing code, by leveraging LLMs as the “brains” of the development process. We adopt a broad survey methodology, categorizing platforms based on key dimensions such as interface style, backend integration, output type, and extensibility. We cover both dedicated LLM-based app builders (e.g., OpenAI’s custom GPTs, Bolt.new, Dust.tt, Flowise, Cognosys) and general no-code platforms (e.g., Bubble, Glide) that integrate LLM capabilities. We present a taxonomy categorizing these platforms by their interface (conversational, visual, etc.), supported LLM backends, output type (chatbot, full application, workflow), and degree of extensibility. Core features such as autonomous agents, memory management, workflow orchestration, and API integrations are examined. We provide a detailed comparison, highlighting each platform’s strengths and limitations. Trade-offs (customizability, scalability, vendor lock-in) are discussed in comparison with traditional and low-code development approaches. Finally, we outline future directions-including multimodal interfaces, on-device LLMs, and improved orchestration for democratizing app creation with AI. Our findings indicate that while zero-code LLM platforms greatly lower the barrier to creating AI-powered applications, they still face challenges in flexibility and reliability. Overall, the landscape is rapidly evolving, offering exciting opportunities to emp... | T10: Include | U10: 5 | V10: Core focus | W10: Review of Tools for Zero-Code LLM Based Application Development | X10: AI and automation | Y10: Platform comparison; Integration; Vendor lock-in | Z10: Supports review questions on LCNC adoption, AI automation, methods, benefits, risks, and gaps depending on assigned theme codes. | AA10: Our findings indicate that while zero-code LLM platforms greatly lower the barrier to creating AI-powered applications, they still face challenges in flexibility and reliability. | No-code configurations may lack versioning, testability, or debugging tools found in traditional development [30]. | We found that while these platforms differ in approach, they all aim to make LLM-powered development accessible without coding. | AB10: 1 Introduction The rise of no-code and low-code development platforms has significantly lowered the barrier for non-programmers to create software [1]. | AC10: We cover both dedicated LLM-based app builders (e.g., OpenAI’s custom GPTs, Bolt.new, Dust.tt, Flowise, Cognosys) and general no-code platforms (e.g., Bubble, Glide) that integrate LLM capabilities. | AD10: low-code; no-code; visual programming; zero-code | AE10: We observe that platforms like LangFlow/Flowise or Dust-influenced by AI developer frameworks-provide more robust control flow constructs for AI-driven logic, whereas pure no-code solutions lean on the LLM’s internal decision-making or simpler sequential triggers [11]. | AF10: Large Language Models, Citation Generation, Retrieval-Augmented Generation, AI Ethics, Multimodal LLMs, Evaluation Metrics. 1 | AG10: .Large Language Models (LLMs) are transforming software creation by enabling zero-code development platforms. This survey reviews recent platforms that let users build applications without writing code, by leveraging LLMs as the “brains” of the development process. We adopt a broad survey methodology, categorizing platforms based on key dimensions such as interface style, backend integration, output type, and extensibility. We cover both dedicated LLM-based app builders (e.g., OpenAI’s custom GPTs, Bolt.new, Dust.tt, Flowise, Cognosys) and general no-code platforms (e.g., Bubble, Glide) that integrate LLM capabilities. We present a taxonomy categorizing these platforms by their interface (conversational, visual, etc.), supported LLM backends, output type (chatbot, full application, workflow), and degree of extensibility. Core features such as autonomous agents, memory management, workflow orchestration, and API integrations are examined. We provide a detailed comparison, highlighting each platform’s strengths and limitations. Trade-offs (customizability, scalability, vendor lock-in) are discussed in comparison with traditional and low-code development approaches. Finally, we outline future directions-including multimodal interfaces, on-device LLMs, and improved orchestration for democratizing app creation with AI. Our findings indicate that while zero-code LLM platforms greatly lower the barrier to creating AI-powered applications, they still face challenges in flexibility and reliability. Overall, the landscape is rapidly evolving, offering exciting opportunities to emp... | AH10: Literature Review | AI10: Review | AJ10: Literature Review | AK10: Literature Review | AL10: Secondary Data | AM10: Published studies/articles | AN10: Not reported | AO10: Not reported | AP10: This survey reviews recent platforms that let users build applications without writing code, by leveraging LLMs as the “brains” of the development process. | AQ10: Power Apps; Mendix; OutSystems; ChatGPT | AR10: Power Apps; Mendix; OutSystems; ChatGPT | AS10: Not reported | AT10: Flowise is an example offering a visual flow builder: users connect nodes representing LLMs, tools, or data sources to define an AI workflow (similar to Node-RED or BPMN for AI) [14]. | AU10: Not reported | AV10: Microsoft’s Power Apps Copilot [18] similarly “generates the app for you based on your description”, creating screens and a data model from a prompt. | AW10: This survey reviews recent platforms that let users build applications without writing code, by leveraging LLMs as the “brains” of the development process. | AX10: Not reported | AY10: Not reported | AZ10: Review of Tools for Zero-Code LLM Based Application Development Priyaranjan Pattnayak1 and Hussain Bohra 2 1 University of Washington, Seattle, USA, ppattnay@uw.edu, 2 SVKM’s Narsee Monjee Institute of Management Studies, Mumbai, India, hussainbohra@gmail.com Abstract.Large Language Models (LLMs) are transforming software creation by enabling zero-code development platforms. | BA10: Not reported | BB10: Keywords:Large Language Models, Citation Generation, Retrieval-Augmented Generation, AI Ethics, Multimodal LLMs, Evaluation Metrics. | BC10: Our findings indicate that while zero-code LLM platforms greatly lower the barrier to creating AI-powered applications, they still face challenges in flexibility and reliability. | BD10: Our findings indicate that while zero-code LLM platforms greatly lower the barrier to creating AI-powered applications, they still face challenges in flexibility and reliability. | No-code configurations may lack versioning, testability, or debugging tools found in traditional development [30]. | We found that while these platforms differ in approach, they all aim to make LLM-powered development accessible without coding. | BE10: Finally, we outline future directions-including multimodal interfaces, on-device LLMs, and improved orchestration for democratizing app creation with AI. | Overall, the landscape is rapidly evolving, offering exciting opportunities to empower non-programmers to create sophisticated software. | BF10: We provide a detailed comparison, highlighting each platform’s strengths and limitations. | Our findings indicate that while zero-code LLM platforms greatly lower the barrier to creating AI-powered applications, they still face challenges in flexibility and reliability. | BG10: However, as smaller efficient models (e.g., Llama 2 variants) become available, future platforms might let users run LLMs locally or in a private cloud for data privacy [16]. | BH10: For sensitive use cases, organizations may need enterprise-grade features like private deployments or strict data governance policies. | BI10: Trade-offs (customizability, scalability, vendor lock-in) are discussed in comparison with traditional and low-code development approaches. | It is crucial to understand the limitations in terms of customizability, performance, scalability, and maintenance when relying on these higher-level tools. | BJ10: In essence, LLMs enable natural language-driven development, turning vague ideas into functional prototypes faster than ever [7]. | BK10: This adds complexity in testing and validation. | BL10: However, even professional developers may use LLM tools to avoid boilerplate, treating them as accelerators for repetitive patterns [31]. | BM10: We highlight six key capabilities: support for autonomous agents (tool use and multi-step reasoning), memory and knowledge integration, workflow logic and control, integration with external services via APIs, and other notable features (like multimodal inputs or training customization) [3, 8-12, 14, 18]. | BN10: Review of Tools for Zero-Code LLM Based Application Development Priyaranjan Pattnayak1 and Hussain Bohra 2 1 University of Washington, Seattle, USA, ppattnay@uw.edu, 2 SVKM’s Narsee Monjee Institute of Management Studies, Mumbai, India, hussainbohra@gmail.com Abstract.Large Language Models (LLMs) are transforming software creation by enabling zero-code development platforms. | BO10: Such platforms often allow switching between providers (OpenAI, Anthropic, etc.) or even using open-source models, which can be beneficial for cost and flexibility. •An emerging aspect is on-device or private LLM support. | BP10: However, until recently, the complexity of custom logic still posed challenges-anything beyond simple workflows often required some coding or technical expertise. | BQ10: Our findings indicate that while zero-code LLM platforms greatly lower the barrier to creating AI-powered applications, they still face challenges in flexibility and reliability. | No-code configurations may lack versioning, testability, or debugging tools found in traditional development [30]. | We found that while these platforms differ in approach, they all aim to make LLM-powered development accessible without coding. | BR10: Finally, we outline future directions-including multimodal interfaces, on-device LLMs, and improved orchestration for democratizing app creation with AI. | BS10: 1 | BT10: We provide a detailed comparison, highlighting each platform’s strengths and limitations. | BU10: 1 | BV10: Not reported | BW10: Not reported | BX10: Moderate | BY10: PDF text extracted from 19 pages; sample evidence page: Not reported. | BZ10: . Trade-offs (customizability, scalability, vendor lock-in) are discussed in comparison with traditional and low-code development approaches. Finally, we outline future directions-including multimodal interfaces, on-device LLMs, and improved orchestration for democratizing app creation with AI. Our findings indicate that while zero-code LLM platforms greatly lower the barrier to creating AI-powered applications, they still face challenges in flexibility and reliability. Overall, the landscape is rapidly evolving, offering exciting opportunities to empower non-programmers to create sophisticated software. Keywords:Large Language Models, Citation Generation, Retrieval-Augmented Generation, AI Ethics, Multimodal LLMs, Evaluation Metrics. 1 Introduction The rise of no-code and low-code development platforms has significantly lowered the barrier for non-programmers to create software [1]. By providing visual interfaces, templates, and pre-built components, these platforms have democratized app development, enabling “citizen developers” to build and deploy applications arXiv:2510.19747v1 [cs.SE] 22 Oct 2025 2 Pattnayak et al. without traditional coding [2]. However, until recently, the complexity of custom logic still posed challenges-anything beyond simple workflows often required some coding or technical expertise. Large Language Models (LLMs) have emerged as a game-changer in t... | CA10: Sample/data adequacy could not be verified from parsed text | CB10: . Trade-offs (customizability, scalability, vendor lock-in) are discussed in comparison with traditional and low-code development approaches. Finally, we outline future directions-including multimodal interfaces, on-device LLMs, and improved orchestration for democratizing app creation with AI. Our findings indicate that while zero-code LLM platforms greatly lower the barrier to creating AI-powered applications, they still face challenges in flexibility and reliability. Overall, the landscape is rapidly evolving, offering exciting opportunities to empower non-programmers to create sophisticated software. Keywords:Large Language Models, Citation Generation, Retrieval-Augmented Generation, AI Ethics, Multimodal LLMs, Evaluation Metrics. 1 Introduction The rise of no-code and low-code development platforms has significantly lowered the barrier for non-programmers to create software [1]. By providing visual interfaces, templates, and pre-built components, these platforms have democratized app development, enabling “citizen developers” to build and deploy applications arXiv:2510.19747v1 [cs.SE] 22 Oct 2025 2 Pattnayak et al. without traditional coding [2]. However, until recently, the complexity of custom logic still posed challenges-anything beyond simple workflows often required some coding or technical expertise. Large Language Models (LLMs) have emerged as a game-changer in t... | CC10: Not reported | CD10: For sensitive use cases, organizations may need enterprise-grade features like private deployments or strict data governance policies. | CE10: Not reported | CF10: For sensitive use cases, organizations may need enterprise-grade features like private deployments or strict data governance policies. | CG10: AI_AUTOMATION | CH10: PLATFORM_COMPARISON | CI10: INTEGRATION | CJ10: VENDOR_LOCKIN | CK10: Literature Review | CL10: Not reported | CM10: =IFERROR(VLOOKUP($A10,Quality_Appraisal!$A:$P,15,FALSE),"") -> 22 | CN10: =IFERROR(VLOOKUP($A10,Quality_Appraisal!$A:$P,16,FALSE),"") -> Strong | CO10: Yes - central | CP10: Findings/Future | CQ10: Our findings indicate that while zero-code LLM platforms greatly lower the barrier to creating AI-powered applications, they still face challenges in flexibility and reliability. | No-code configurations may lack versioning, testability, or debugging tools found in traditional development [30]. | We found that while these platforms differ in approach, they all aim to make LLM-powered development accessible without coding. | CR10: Not reported | CS10: AI and automation | CT10: Our findings indicate that while zero-code LLM platforms greatly lower the barrier to creating AI-powered applications, they still face challenges in flexibility and reliability. | No-code configurations may lack versioning, testability, or debugging tools found in traditional development [30]. | We found that while these platforms differ in approach, they all aim to make LLM-powered development accessible without coding. | CU10: sample/data size missing | CV10: Not reported | CW10: Application Development; Priyaranjan Pattnayak1 and Hussain Bohra 2 (2025). Review of Tools for Zero-Code LLM Based Application Development. arXiv:2510.19747v1 [cs.SE] 22 Oct 2025. | CX10: Not reported
A11: P010 | B11: 10.LArc_ICSA2025__Towards_AI_powered_consistency_keeping_in_model_based_low_code_platforms.pdf | C11: research paper\10.LArc_ICSA2025__Towards_AI_powered_consistency_keeping_in_model_based_low_code_platforms.pdf | D11: Completed | E11: 2026-06-12 | F11: Checked - OK | G11: Reported | H11: 4 | I11: Verify automated title/authors/method/sample/theme coding and exact quote page numbers before publication use. | J11: Not reported | K11: Towards LLM-powered consistency in model-based low-code platforms | L11: Nathan Hagel; Nicolas Hili; Univ. Grenoble Alpes, CNRS | M11: 2005 | N11: Not reported | O11: © 2025 IEEE. Personal use of this material is permitted. Permission from IEEE must be obtained for all other uses, in any current or future media, including reprinting/republishing this | P11: IEEE | Q11: Unclear: discipline not explicitly labeled; paper text concerns LCNC/software systems | R11: LLM, AI, low-code development platform, metamodel, model-driven engineering, DSL, consistency I. I NTRODUCTION To shorten the development time of software applications, low-code platforms can enable citizen developers (developers with little or no software engineering background [1]), such as domain experts, to build functional applications effecti | S11: Low-code platforms often use various models that define the application built by citizen developers. With the increasing size and complexity of the applications built using low-code platforms, the number of required models and the dependencies between them expand. However, with increased complexity, keeping these models consistent during the development or evolution of the application is crucial and often a non-trivial task for citizen developers. In this paper, we present four approaches to how LLMs can be used and integrated on the architecture level into low-code platforms to (i) create consistent models automatically, (ii) keep models consistent based on different types of dependencies, and (iii) support users in maintaining consistent models during the development. We implemented the approaches in a prototype and evaluated them in an exploratory study. The results show that state-of-the-art LLMs are capable of preserving consistency for low-code models as well as generating correct and consistent models in various scenarios. | T11: Include | U11: 5 | V11: Core focus | W11: Towards LLM-powered consistency in model-based low-code platforms | X11: Model-driven / visual programming roots | Y11: AI and automation; Citizen development; Usability and user experience | Z11: Supports review questions on LCNC adoption, AI automation, methods, benefits, risks, and gaps depending on assigned theme codes. | AA11: The results show that state-of-the-art LLMs are capable of preserving consistency for low-code models as well as generating correct and consistent models in various scenarios. | In any This work was funded by the Deutsche Forschungsgemeinschaft (DFG, German Research Foundation) - SFB 1608 - 501798263 case, the code is generated from a model-like artifact or a set of artifacts. | We evaluate the approaches in Section V and discuss the findings in Section VI. | AB11: Towards LLM-powered consistency in model-based low-code platforms 1st Nathan Hagel KASTEL Karlsruhe Institute of Technology Karlsruhe, Germany nathan.hagel@kit.edu 2nd Nicolas Hili Univ. | AC11: Not reported | AD11: low-code; model-driven engineering | AE11: Using custom DSLs usually means that a metamodel is defined (e.g., using Eclipse Modeling Framework (EMF) [10] or FlexiMeta [11]) to formalize the DSL. | AF11: LLM, AI, low-code development platform, metamodel, model-driven engineering, DSL, consistency I. I NTRODUCTION To shorten the development time of software applications, low-code platforms can enable citizen developers (developers with little or no software engineering background [1]), such as domain experts, to build functional applications effecti | AG11: Low-code platforms often use various models that define the application built by citizen developers. With the increasing size and complexity of the applications built using low-code platforms, the number of required models and the dependencies between them expand. However, with increased complexity, keeping these models consistent during the development or evolution of the application is crucial and often a non-trivial task for citizen developers. In this paper, we present four approaches to how LLMs can be used and integrated on the architecture level into low-code platforms to (i) create consistent models automatically, (ii) keep models consistent based on different types of dependencies, and (iii) support users in maintaining consistent models during the development. We implemented the approaches in a prototype and evaluated them in an exploratory study. The results show that state-of-the-art LLMs are capable of preserving consistency for low-code models as well as generating correct and consistent models in various scenarios. | AH11: Tool/Platform Proposal | AI11: Technical/Engineering | AJ11: Prototype Evaluation | AK11: Prototype Evaluation | AL11: Primary Data | AM11: Prototype/tool/platform or benchmark tasks | AN11: Not reported | AO11: Not reported | AP11: Information Management Neu-Ulm University of Applied Sciences Neu-Ulm, Germany alexander.bartel@hnu.de 4th Anne Koziolek KASTEL Karlsruhe Institute of Technology Karlsruhe, Germany anne.koziolek@kit.edu Abstract-Low-code platforms often use various models that define the application built by citizen developers. | AQ11: ChatGPT | AR11: ChatGPT | AS11: In the context of lowcode platforms, the question of how such mechanisms can be integrated and which work best in different scenarios is still an open research question. | Such work would contribute to the research question of which approach is best and when LLMbased consistency preserving mechanisms are applicable. | AT11: However, it comes with significant challenges, primarily the need for large and often expensive-to-create datasets to achieve effective fine-tuning [15], [16]. | AU11: Not reported | AV11: Additionally, well-formed rules and even relations to other meta-models / meta-classes can be added to a metamodel’s specification, establishing the criteria for valid models. | AW11: Information Management Neu-Ulm University of Applied Sciences Neu-Ulm, Germany alexander.bartel@hnu.de 4th Anne Koziolek KASTEL Karlsruhe Institute of Technology Karlsruhe, Germany anne.koziolek@kit.edu Abstract-Low-code platforms often use various models that define the application built by citizen developers. | AX11: Not reported | AY11: Not reported | AZ11: By leveraging LLMs, the development effort required for implementing consistency mechanisms could be significantly reduced while enhancing the tools available for citizen developers and facilitating more efficient application creation. | BA11: Not reported | BB11: We implemented the approaches in a prototype and evaluated them in an exploratory study. | BC11: Not reported | BD11: The results show that state-of-the-art LLMs are capable of preserving consistency for low-code models as well as generating correct and consistent models in various scenarios. | In any This work was funded by the Deutsche Forschungsgemeinschaft (DFG, German Research Foundation) - SFB 1608 - 501798263 case, the code is generated from a model-like artifact or a set of artifacts. | We evaluate the approaches in Section V and discuss the findings in Section VI. | BE11: AI-assisted low-code platforms can help citizen developers to create applications faster [4]. | By leveraging LLMs, the development effort required for implementing consistency mechanisms could be significantly reduced while enhancing the tools available for citizen developers and facilitating more efficient application creation. | BF11: However, with increased complexity, keeping these models consistent during the development or evolution of the application is crucial and often a non-trivial task for citizen developers. | However, keeping the models consistent is still a challenging task. | BG11: Not reported | BH11: The user can then decide if the change is accepted or ignored while keeping complete control over the models. | BI11: However, with increased complexity, keeping these models consistent during the development or evolution of the application is crucial and often a non-trivial task for citizen developers. | BJ11: AI-assisted low-code platforms can help citizen developers to create applications faster [4]. | BK11: Therefore, when testing the approaches, we targeted the question, if we can find working prompts for each of these approaches. | BL11: As low-code platforms target citizen developers with no programming skills, models are often used to abstract away the complexity of writing code manually. | BM11: Not reported | BN11: In this paper, we present four approaches to how LLMs can be used and integrated on the architecture level into low-code platforms to (i) create consistent models automatically, (ii) keep models consistent based on different types of dependencies, and (iii) support users in maintaining consistent models during the development. | BO11: This means that the computational overhead and therefore costs introduced to the LCDP is probably higher than with approach A. | BP11: However, with increased complexity, keeping these models consistent during the development or evolution of the application is crucial and often a non-trivial task for citizen developers. | BQ11: The results show that state-of-the-art LLMs are capable of preserving consistency for low-code models as well as generating correct and consistent models in various scenarios. | In any This work was funded by the Deutsche Forschungsgemeinschaft (DFG, German Research Foundation) - SFB 1608 - 501798263 case, the code is generated from a model-like artifact or a set of artifacts. | We evaluate the approaches in Section V and discuss the findings in Section VI. | BR11: Index Terms-LLM, AI, low-code development platform, metamodel, model-driven engineering, DSL, consistency I. | BS11: 1 | BT11: Index Terms-LLM, AI, low-code development platform, metamodel, model-driven engineering, DSL, consistency I. | BU11: 1 | BV11: Not reported | BW11: Not reported | BX11: Moderate | BY11: PDF text extracted from 6 pages; sample evidence page: Not reported. | BZ11: and compare them with alternatives in preserving consistency in LCDPs. As LLMs are capable of generating syntactically correct models in LCDPs [4], [21], [22], and our initial experiments show that this is most likely also the case when generating a set of models with dependencies between each other, using LLMs for consistency preservation in LCDPs seems to be a valid option for platform developers. However, the approaches have a different impact on the platform and how the platforms are used and also require some technical aspects that should be integrated on the architecture level of a LCDP. Previous work [4] showed that adding LLMs in a chat-like interface similar to known providers such as ChatGPT [13] can increase the perceived usability and efficiency of LCDPs. This can be said not only for directly generating models or other artifacts but also for helpful chatbots that answer questions. Extending this work by generating all models and keeping them consistent in the development process should have a similar effect. This means that approach A - generating consistent models or generating the desired change described in natural language (see Figure 1 left side - A) - should be a valid choice for LCDP developers. However, an approach like this can change the use or the process how applications are created in the LCDP. One concern would be that the user could lose the overv... | CA11: Sample/data adequacy could not be verified from parsed text | CB11: . | CC11: . | CD11: Not reported | CE11: Not reported | CF11: The user can then decide if the change is accepted or ignored while keeping complete control over the models. | CG11: MDE_VISUAL_PROGRAMMING | CH11: AI_AUTOMATION | CI11: CITIZEN_DEV | CJ11: USABILITY_UX | CK11: Prototype Evaluation | CL11: Not reported | CM11: =IFERROR(VLOOKUP($A11,Quality_Appraisal!$A:$P,15,FALSE),"") -> 21 | CN11: =IFERROR(VLOOKUP($A11,Quality_Appraisal!$A:$P,16,FALSE),"") -> Strong | CO11: Yes - central | CP11: Background | CQ11: The results show that state-of-the-art LLMs are capable of preserving consistency for low-code models as well as generating correct and consistent models in various scenarios. | In any This work was funded by the Deutsche Forschungsgemeinschaft (DFG, German Research Foundation) - SFB 1608 - 501798263 case, the code is generated from a model-like artifact or a set of artifacts. | We evaluate the approaches in Section V and discuss the findings in Section VI. | CR11: Not reported | CS11: Model-driven / visual programming roots | CT11: The results show that state-of-the-art LLMs are capable of preserving consistency for low-code models as well as generating correct and consistent models in various scenarios. | In any This work was funded by the Deutsche Forschungsgemeinschaft (DFG, German Research Foundation) - SFB 1608 - 501798263 case, the code is generated from a model-like artifact or a set of artifacts. | We evaluate the approaches in Section V and discuss the findings in Section VI. | CU11: sample/data size missing | CV11: Not reported | CW11: Nathan Hagel; Nicolas Hili; Univ. Grenoble Alpes, CNRS (2005). Towards LLM-powered consistency in model-based low-code platforms. © 2025 IEEE. Personal use of this material is permitted. Permission from IEEE must be obtained for all other uses, in any current or future media, including reprinting/republishing this. | CX11: Not reported
